{
  "state": "IA",
  "state_name": "Iowa",
  "utility_count": 155,
  "total_residential_customers": 1402574,
  "avg_residential_rate": 0.1013,
  "net_metering_policy": {
    "type": "NEM",
    "statewide": true
  },
  "total_solar_installations": 12561,
  "total_solar_capacity_mw": 108.49,
  "utilities": [
    {
      "utility_id": "12341",
      "utility_name": "MidAmerican Energy Co",
      "state": "IA",
      "ownership_type": "IOU",
      "customer_count": 632436,
      "residential_rate_per_kwh": 0.1101,
      "rate_data_source": "EIA-861",
      "rate_structure": "tou",
      "tou_available": true,
      "demand_charges": false,
      "has_net_metering": true,
      "net_metering_type": "NEM",
      "net_metering_note": null,
      "solar_installations": 520,
      "solar_capacity_mw": 4.255,
      "urdb_rate_name": "RATE RS - RESIDENTIAL SERVICE",
      "urdb_rate_per_kwh": 0.0906,
      "updated_at": "2026-02-09"
    },
    {
      "utility_id": "9417",
      "utility_name": "Interstate Power and Light Co",
      "state": "IA",
      "ownership_type": "IOU",
      "customer_count": 417153,
      "residential_rate_per_kwh": 0.179,
      "rate_data_source": "EIA-861",
      "rate_structure": "tou",
      "tou_available": true,
      "demand_charges": false,
      "has_net_metering": true,
      "net_metering_type": "NEM",
      "net_metering_note": null,
      "solar_installations": 10120,
      "solar_capacity_mw": 82.574,
      "urdb_rate_name": "Electric Residential Service Usage - 400",
      "urdb_rate_per_kwh": 0.1676,
      "updated_at": "2026-02-09"
    },
    {
      "utility_id": "99999",
      "utility_name": "Adjustment 2024",
      "state": "IA",
      "ownership_type": "other",
      "customer_count": 159287,
      "residential_rate_per_kwh": 0.1348,
      "rate_data_source": "EIA-861",
      "rate_structure": "unknown",
      "tou_available": false,
      "demand_charges": false,
      "has_net_metering": true,
      "net_metering_type": "NEM",
      "net_metering_note": null,
      "solar_installations": 0,
      "solar_capacity_mw": -1.584,
      "urdb_rate_name": null,
      "urdb_rate_per_kwh": null,
      "updated_at": "2026-02-09"
    },
    {
      "utility_id": "11053",
      "utility_name": "Linn County REC",
      "state": "IA",
      "ownership_type": "cooperative",
      "customer_count": 30323,
      "residential_rate_per_kwh": 0.1423,
      "rate_data_source": "EIA-861",
      "rate_structure": "tou",
      "tou_available": true,
      "demand_charges": false,
      "has_net_metering": true,
      "net_metering_type": "NEM",
      "net_metering_note": null,
      "solar_installations": 638,
      "solar_capacity_mw": 5.153,
      "urdb_rate_name": "Residential Time of Day",
      "urdb_rate_per_kwh": 0.1072,
      "updated_at": "2026-02-09"
    },
    {
      "utility_id": "554",
      "utility_name": "City of Ames - (IA)",
      "state": "IA",
      "ownership_type": "municipal",
      "customer_count": 24979,
      "residential_rate_per_kwh": 0.121,
      "rate_data_source": "EIA-861",
      "rate_structure": "tou",
      "tou_available": true,
      "demand_charges": false,
      "has_net_metering": true,
      "net_metering_type": "NEM",
      "net_metering_note": null,
      "solar_installations": 210,
      "solar_capacity_mw": 0.884,
      "urdb_rate_name": "Residential",
      "urdb_rate_per_kwh": 0.1066,
      "updated_at": "2026-02-09"
    },
    {
      "utility_id": "5605",
      "utility_name": "Eastern Iowa Light & Power Coop",
      "state": "IA",
      "ownership_type": "cooperative",
      "customer_count": 20749,
      "residential_rate_per_kwh": 0.1356,
      "rate_data_source": "EIA-861",
      "rate_structure": "unknown",
      "tou_available": false,
      "demand_charges": false,
      "has_net_metering": true,
      "net_metering_type": "NEM",
      "net_metering_note": null,
      "solar_installations": 298,
      "solar_capacity_mw": 3.256,
      "urdb_rate_name": null,
      "urdb_rate_per_kwh": null,
      "updated_at": "2026-02-09"
    },
    {
      "utility_id": "3203",
      "utility_name": "Cedar Falls Utilities",
      "state": "IA",
      "ownership_type": "municipal",
      "customer_count": 17772,
      "residential_rate_per_kwh": 0.1042,
      "rate_data_source": "EIA-861",
      "rate_structure": "tou",
      "tou_available": true,
      "demand_charges": false,
      "has_net_metering": true,
      "net_metering_type": "NEM",
      "net_metering_note": null,
      "solar_installations": 72,
      "solar_capacity_mw": 0.576,
      "urdb_rate_name": "Residential",
      "urdb_rate_per_kwh": 0.0579,
      "updated_at": "2026-02-09"
    },
    {
      "utility_id": "12450",
      "utility_name": "Midland Power Coop",
      "state": "IA",
      "ownership_type": "cooperative",
      "customer_count": 11939,
      "residential_rate_per_kwh": 0.136,
      "rate_data_source": "EIA-861",
      "rate_structure": "unknown",
      "tou_available": false,
      "demand_charges": false,
      "has_net_metering": true,
      "net_metering_type": "NEM",
      "net_metering_note": null,
      "solar_installations": 18,
      "solar_capacity_mw": 0.199,
      "urdb_rate_name": null,
      "urdb_rate_per_kwh": null,
      "updated_at": "2026-02-09"
    },
    {
      "utility_id": "12642",
      "utility_name": "Maquoketa Valley Rrl Elec Coop",
      "state": "IA",
      "ownership_type": "cooperative",
      "customer_count": 11051,
      "residential_rate_per_kwh": 0.1376,
      "rate_data_source": "EIA-861",
      "rate_structure": "unknown",
      "tou_available": false,
      "demand_charges": false,
      "has_net_metering": true,
      "net_metering_type": "NEM",
      "net_metering_note": null,
      "solar_installations": 0,
      "solar_capacity_mw": 0,
      "urdb_rate_name": null,
      "urdb_rate_per_kwh": null,
      "updated_at": "2026-02-09"
    },
    {
      "utility_id": "13143",
      "utility_name": "Board of Water Electric & Communications",
      "state": "IA",
      "ownership_type": "municipal",
      "customer_count": 10123,
      "residential_rate_per_kwh": 0.1263,
      "rate_data_source": "EIA-861",
      "rate_structure": "flat",
      "tou_available": false,
      "demand_charges": false,
      "has_net_metering": true,
      "net_metering_type": "NEM",
      "net_metering_note": null,
      "solar_installations": 26,
      "solar_capacity_mw": 0.2,
      "urdb_rate_name": "Residential Electric",
      "urdb_rate_per_kwh": 0.0828,
      "updated_at": "2026-02-09"
    },
    {
      "utility_id": "9425",
      "utility_name": "Iowa Lakes Electric Coop",
      "state": "IA",
      "ownership_type": "cooperative",
      "customer_count": 9714,
      "residential_rate_per_kwh": 0.1378,
      "rate_data_source": "EIA-861",
      "rate_structure": "unknown",
      "tou_available": false,
      "demand_charges": false,
      "has_net_metering": true,
      "net_metering_type": "NEM",
      "net_metering_note": null,
      "solar_installations": 53,
      "solar_capacity_mw": 1.055,
      "urdb_rate_name": null,
      "urdb_rate_per_kwh": null,
      "updated_at": "2026-02-09"
    },
    {
      "utility_id": "17260",
      "utility_name": "North West Rural Electric Coop",
      "state": "IA",
      "ownership_type": "cooperative",
      "customer_count": 9400,
      "residential_rate_per_kwh": 0.0926,
      "rate_data_source": "EIA-861",
      "rate_structure": "tiered",
      "tou_available": false,
      "demand_charges": false,
      "has_net_metering": true,
      "net_metering_type": "NEM",
      "net_metering_note": null,
      "solar_installations": 14,
      "solar_capacity_mw": 0.179,
      "urdb_rate_name": "Residential - Single Phase Service Rate",
      "urdb_rate_per_kwh": 0.108,
      "updated_at": "2026-02-09"
    },
    {
      "utility_id": "16611",
      "utility_name": "Access Energy Coop",
      "state": "IA",
      "ownership_type": "cooperative",
      "customer_count": 8850,
      "residential_rate_per_kwh": 0.1495,
      "rate_data_source": "EIA-861",
      "rate_structure": "flat",
      "tou_available": false,
      "demand_charges": false,
      "has_net_metering": true,
      "net_metering_type": "NEM",
      "net_metering_note": null,
      "solar_installations": 0,
      "solar_capacity_mw": 0,
      "urdb_rate_name": "Residential Single Phase Rate",
      "urdb_rate_per_kwh": 0.0904,
      "updated_at": "2026-02-09"
    },
    {
      "utility_id": "5588",
      "utility_name": "East-Central Iowa Rural Elec Coop",
      "state": "IA",
      "ownership_type": "cooperative",
      "customer_count": 7368,
      "residential_rate_per_kwh": 0.1328,
      "rate_data_source": "EIA-861",
      "rate_structure": "tiered",
      "tou_available": false,
      "demand_charges": false,
      "has_net_metering": true,
      "net_metering_type": "NEM",
      "net_metering_note": null,
      "solar_installations": 6,
      "solar_capacity_mw": 0.072,
      "urdb_rate_name": "Rural Farm and Residential Service 25-50 kVA",
      "urdb_rate_per_kwh": 0.1133,
      "updated_at": "2026-02-09"
    },
    {
      "utility_id": "11788",
      "utility_name": "Consumers Energy Coop - (IA)",
      "state": "IA",
      "ownership_type": "cooperative",
      "customer_count": 6922,
      "residential_rate_per_kwh": 0.15,
      "rate_data_source": "EIA-861",
      "rate_structure": "flat",
      "tou_available": false,
      "demand_charges": false,
      "has_net_metering": true,
      "net_metering_type": "NEM",
      "net_metering_note": null,
      "solar_installations": 16,
      "solar_capacity_mw": 0.181,
      "urdb_rate_name": "Rate Schedule",
      "urdb_rate_per_kwh": 0.1225,
      "updated_at": "2026-02-09"
    },
    {
      "utility_id": "19157",
      "utility_name": "MiEnergy Cooperative",
      "state": "IA",
      "ownership_type": "cooperative",
      "customer_count": 6006,
      "residential_rate_per_kwh": 0.1691,
      "rate_data_source": "EIA-861",
      "rate_structure": "tou",
      "tou_available": true,
      "demand_charges": false,
      "has_net_metering": true,
      "net_metering_type": "NEM",
      "net_metering_note": null,
      "solar_installations": 391,
      "solar_capacity_mw": 7.825,
      "urdb_rate_name": "Interruptible Heating - Single Phase",
      "urdb_rate_per_kwh": 0.085,
      "updated_at": "2026-02-09"
    },
    {
      "utility_id": "8319",
      "utility_name": "Heartland Power Coop",
      "state": "IA",
      "ownership_type": "cooperative",
      "customer_count": 4351,
      "residential_rate_per_kwh": 0.1267,
      "rate_data_source": "EIA-861",
      "rate_structure": "tou",
      "tou_available": true,
      "demand_charges": false,
      "has_net_metering": true,
      "net_metering_type": "NEM",
      "net_metering_note": null,
      "solar_installations": 1,
      "solar_capacity_mw": 0.008,
      "urdb_rate_name": "Interruptible  - Residential (Rate C)",
      "urdb_rate_per_kwh": 0.079,
      "updated_at": "2026-02-09"
    },
    {
      "utility_id": "2652",
      "utility_name": "Butler County Rural Elec Coop - (IA)",
      "state": "IA",
      "ownership_type": "cooperative",
      "customer_count": 3898,
      "residential_rate_per_kwh": 0.1543,
      "rate_data_source": "EIA-861",
      "rate_structure": "tiered",
      "tou_available": false,
      "demand_charges": false,
      "has_net_metering": true,
      "net_metering_type": "NEM",
      "net_metering_note": null,
      "solar_installations": 2,
      "solar_capacity_mw": 0.014,
      "urdb_rate_name": "Regular Farm and Residential Single Phase",
      "urdb_rate_per_kwh": 0.1151,
      "updated_at": "2026-02-09"
    },
    {
      "utility_id": "15291",
      "utility_name": "Prairie Energy Coop",
      "state": "IA",
      "ownership_type": "cooperative",
      "customer_count": 3440,
      "residential_rate_per_kwh": 0.1434,
      "rate_data_source": "EIA-861",
      "rate_structure": "unknown",
      "tou_available": false,
      "demand_charges": false,
      "has_net_metering": true,
      "net_metering_type": "NEM",
      "net_metering_note": null,
      "solar_installations": 3,
      "solar_capacity_mw": 0.021,
      "urdb_rate_name": null,
      "urdb_rate_per_kwh": null,
      "updated_at": "2026-02-09"
    },
    {
      "utility_id": "11611",
      "utility_name": "City of Maquoketa - (IA)",
      "state": "IA",
      "ownership_type": "municipal",
      "customer_count": 2805,
      "residential_rate_per_kwh": 0.1315,
      "rate_data_source": "EIA-861",
      "rate_structure": "unknown",
      "tou_available": false,
      "demand_charges": false,
      "has_net_metering": true,
      "net_metering_type": "NEM",
      "net_metering_note": null,
      "solar_installations": 8,
      "solar_capacity_mw": 0.207,
      "urdb_rate_name": null,
      "urdb_rate_per_kwh": null,
      "updated_at": "2026-02-09"
    },
    {
      "utility_id": "9230",
      "utility_name": "City of Independence - (IA)",
      "state": "IA",
      "ownership_type": "municipal",
      "customer_count": 2719,
      "residential_rate_per_kwh": 0.1382,
      "rate_data_source": "EIA-861",
      "rate_structure": "flat",
      "tou_available": false,
      "demand_charges": false,
      "has_net_metering": true,
      "net_metering_type": "NEM",
      "net_metering_note": null,
      "solar_installations": 7,
      "solar_capacity_mw": 0.033,
      "urdb_rate_name": "Residential Rate",
      "urdb_rate_per_kwh": 0.1348,
      "updated_at": "2026-02-09"
    },
    {
      "utility_id": "471",
      "utility_name": "Amana Society Service Co",
      "state": "IA",
      "ownership_type": "IOU",
      "customer_count": 709,
      "residential_rate_per_kwh": 0.1553,
      "rate_data_source": "EIA-861",
      "rate_structure": "tiered",
      "tou_available": false,
      "demand_charges": false,
      "has_net_metering": true,
      "net_metering_type": "NEM",
      "net_metering_note": null,
      "solar_installations": 0,
      "solar_capacity_mw": 0,
      "urdb_rate_name": "Residential Service",
      "urdb_rate_per_kwh": 0.107,
      "updated_at": "2026-02-09"
    },
    {
      "utility_id": "15349",
      "utility_name": "City of Preston",
      "state": "IA",
      "ownership_type": "municipal",
      "customer_count": 521,
      "residential_rate_per_kwh": 0.1539,
      "rate_data_source": "EIA-861",
      "rate_structure": "flat",
      "tou_available": false,
      "demand_charges": false,
      "has_net_metering": true,
      "net_metering_type": "NEM",
      "net_metering_note": null,
      "solar_installations": 2,
      "solar_capacity_mw": 0.014,
      "urdb_rate_name": "Residential Rate",
      "urdb_rate_per_kwh": 0.125,
      "updated_at": "2026-02-09"
    },
    {
      "utility_id": "6258",
      "utility_name": "Federated Rural Electric Assn",
      "state": "IA",
      "ownership_type": "cooperative",
      "customer_count": 53,
      "residential_rate_per_kwh": 0.1182,
      "rate_data_source": "EIA-861",
      "rate_structure": "tiered",
      "tou_available": false,
      "demand_charges": false,
      "has_net_metering": true,
      "net_metering_type": "NEM",
      "net_metering_note": null,
      "solar_installations": 12,
      "solar_capacity_mw": 0.151,
      "urdb_rate_name": "General Service (Multiphase)-Residential-Wind Energy Electric Service",
      "urdb_rate_per_kwh": 0.0853,
      "updated_at": "2026-02-09"
    },
    {
      "utility_id": "6782",
      "utility_name": "Freeborn Mower Electric Cooperative",
      "state": "IA",
      "ownership_type": "cooperative",
      "customer_count": 6,
      "residential_rate_per_kwh": 0.17,
      "rate_data_source": "EIA-861",
      "rate_structure": "tou",
      "tou_available": true,
      "demand_charges": false,
      "has_net_metering": true,
      "net_metering_type": "NEM",
      "net_metering_note": null,
      "solar_installations": 144,
      "solar_capacity_mw": 3.218,
      "urdb_rate_name": "FARM AND RESIDENTIAL - SINGLE PHASE SERVICE",
      "urdb_rate_per_kwh": 0.1115,
      "updated_at": "2026-02-09"
    },
    {
      "utility_id": "405",
      "utility_name": "City of Alta, Iowa (Utility Company)",
      "state": "IA",
      "ownership_type": "municipal",
      "customer_count": 0,
      "residential_rate_per_kwh": 0.0793,
      "rate_data_source": "OpenEI_URDB",
      "rate_structure": "tiered",
      "tou_available": false,
      "demand_charges": false,
      "has_net_metering": true,
      "net_metering_type": "NEM",
      "net_metering_note": null,
      "solar_installations": 0,
      "solar_capacity_mw": 0,
      "urdb_rate_name": "Residential",
      "urdb_rate_per_kwh": 0.0793,
      "updated_at": "2026-02-09"
    },
    {
      "utility_id": "682",
      "utility_name": "City of Anita, Iowa (Utility Company)",
      "state": "IA",
      "ownership_type": "municipal",
      "customer_count": 0,
      "residential_rate_per_kwh": 0.055,
      "rate_data_source": "OpenEI_URDB",
      "rate_structure": "flat",
      "tou_available": false,
      "demand_charges": false,
      "has_net_metering": true,
      "net_metering_type": "NEM",
      "net_metering_note": null,
      "solar_installations": 0,
      "solar_capacity_mw": 0,
      "urdb_rate_name": "Residential Electric",
      "urdb_rate_per_kwh": 0.055,
      "updated_at": "2026-02-09"
    },
    {
      "utility_id": "700",
      "utility_name": "City of Anthon, Iowa (Utility Company)",
      "state": "IA",
      "ownership_type": "municipal",
      "customer_count": 0,
      "residential_rate_per_kwh": 0.094,
      "rate_data_source": "OpenEI_URDB",
      "rate_structure": "flat",
      "tou_available": false,
      "demand_charges": false,
      "has_net_metering": true,
      "net_metering_type": "NEM",
      "net_metering_note": null,
      "solar_installations": 0,
      "solar_capacity_mw": 0,
      "urdb_rate_name": "Residential Service",
      "urdb_rate_per_kwh": 0.094,
      "updated_at": "2026-02-09"
    },
    {
      "utility_id": "723",
      "utility_name": "City of Aplington, Iowa (Utility Company)",
      "state": "IA",
      "ownership_type": "municipal",
      "customer_count": 0,
      "residential_rate_per_kwh": 0.0872,
      "rate_data_source": "OpenEI_URDB",
      "rate_structure": "tou",
      "tou_available": true,
      "demand_charges": false,
      "has_net_metering": true,
      "net_metering_type": "NEM",
      "net_metering_note": null,
      "solar_installations": 0,
      "solar_capacity_mw": 0,
      "urdb_rate_name": "New Residential Dual Fuel",
      "urdb_rate_per_kwh": 0.0872,
      "updated_at": "2026-02-09"
    },
    {
      "utility_id": "965",
      "utility_name": "Atlantic Municipal Utilities",
      "state": "IA",
      "ownership_type": "municipal",
      "customer_count": 0,
      "residential_rate_per_kwh": 0.0678,
      "rate_data_source": "OpenEI_URDB",
      "rate_structure": "tou",
      "tou_available": true,
      "demand_charges": false,
      "has_net_metering": true,
      "net_metering_type": "NEM",
      "net_metering_note": null,
      "solar_installations": 0,
      "solar_capacity_mw": 0,
      "urdb_rate_name": "Rural All- Electric Residential (Three Phase)",
      "urdb_rate_per_kwh": 0.0678,
      "updated_at": "2026-02-09"
    },
    {
      "utility_id": "1002",
      "utility_name": "City of Aurelia, Iowa (Utility Company)",
      "state": "IA",
      "ownership_type": "municipal",
      "customer_count": 0,
      "residential_rate_per_kwh": 0.0769,
      "rate_data_source": "OpenEI_URDB",
      "rate_structure": "tiered",
      "tou_available": false,
      "demand_charges": false,
      "has_net_metering": true,
      "net_metering_type": "NEM",
      "net_metering_note": null,
      "solar_installations": 0,
      "solar_capacity_mw": 0,
      "urdb_rate_name": "Residential Electric",
      "urdb_rate_per_kwh": 0.0769,
      "updated_at": "2026-02-09"
    },
    {
      "utility_id": "1172",
      "utility_name": "Bancroft Municipal Utilities",
      "state": "IA",
      "ownership_type": "municipal",
      "customer_count": 0,
      "residential_rate_per_kwh": 0.1262,
      "rate_data_source": "OpenEI_URDB",
      "rate_structure": "flat",
      "tou_available": false,
      "demand_charges": false,
      "has_net_metering": true,
      "net_metering_type": "NEM",
      "net_metering_note": null,
      "solar_installations": 0,
      "solar_capacity_mw": 0,
      "urdb_rate_name": "Schedule 1",
      "urdb_rate_per_kwh": 0.1262,
      "updated_at": "2026-02-09"
    },
    {
      "utility_id": "1869",
      "utility_name": "City of Bloomfield, Iowa (Utility Company)",
      "state": "IA",
      "ownership_type": "municipal",
      "customer_count": 0,
      "residential_rate_per_kwh": 0.1208,
      "rate_data_source": "OpenEI_URDB",
      "rate_structure": "flat",
      "tou_available": false,
      "demand_charges": false,
      "has_net_metering": true,
      "net_metering_type": "NEM",
      "net_metering_note": null,
      "solar_installations": 0,
      "solar_capacity_mw": 0,
      "urdb_rate_name": "Residential",
      "urdb_rate_per_kwh": 0.1208,
      "updated_at": "2026-02-09"
    },
    {
      "utility_id": "2183",
      "utility_name": "City of Breda, Iowa (Utility Company)",
      "state": "IA",
      "ownership_type": "municipal",
      "customer_count": 0,
      "residential_rate_per_kwh": 0.1312,
      "rate_data_source": "OpenEI_URDB",
      "rate_structure": "tiered",
      "tou_available": false,
      "demand_charges": false,
      "has_net_metering": true,
      "net_metering_type": "NEM",
      "net_metering_note": null,
      "solar_installations": 0,
      "solar_capacity_mw": 0,
      "urdb_rate_name": "Electric Rate",
      "urdb_rate_per_kwh": 0.1312,
      "updated_at": "2026-02-09"
    },
    {
      "utility_id": "2287",
      "utility_name": "City of Brooklyn, Iowa (Utility Company)",
      "state": "IA",
      "ownership_type": "municipal",
      "customer_count": 0,
      "residential_rate_per_kwh": 0.0968,
      "rate_data_source": "OpenEI_URDB",
      "rate_structure": "tiered",
      "tou_available": false,
      "demand_charges": false,
      "has_net_metering": true,
      "net_metering_type": "NEM",
      "net_metering_note": null,
      "solar_installations": 0,
      "solar_capacity_mw": 0,
      "urdb_rate_name": "Total Electric",
      "urdb_rate_per_kwh": 0.0968,
      "updated_at": "2026-02-09"
    },
    {
      "utility_id": "2600",
      "utility_name": "City of Burt, Iowa (Utility Company)",
      "state": "IA",
      "ownership_type": "municipal",
      "customer_count": 0,
      "residential_rate_per_kwh": 0.111,
      "rate_data_source": "OpenEI_URDB",
      "rate_structure": "tou",
      "tou_available": true,
      "demand_charges": false,
      "has_net_metering": true,
      "net_metering_type": "NEM",
      "net_metering_note": null,
      "solar_installations": 0,
      "solar_capacity_mw": 0,
      "urdb_rate_name": "Power Rate 2",
      "urdb_rate_per_kwh": 0.111,
      "updated_at": "2026-02-09"
    },
    {
      "utility_id": "3029",
      "utility_name": "City of Carlisle, Iowa (Utility Company)",
      "state": "IA",
      "ownership_type": "municipal",
      "customer_count": 0,
      "residential_rate_per_kwh": 0.0987,
      "rate_data_source": "OpenEI_URDB",
      "rate_structure": "tou",
      "tou_available": true,
      "demand_charges": false,
      "has_net_metering": true,
      "net_metering_type": "NEM",
      "net_metering_note": null,
      "solar_installations": 0,
      "solar_capacity_mw": 0,
      "urdb_rate_name": "Residential",
      "urdb_rate_per_kwh": 0.0987,
      "updated_at": "2026-02-09"
    },
    {
      "utility_id": "3111",
      "utility_name": "Cass Electric Coop",
      "state": "IA",
      "ownership_type": "cooperative",
      "customer_count": 0,
      "residential_rate_per_kwh": 0.099,
      "rate_data_source": "OpenEI_URDB",
      "rate_structure": "flat",
      "tou_available": false,
      "demand_charges": false,
      "has_net_metering": true,
      "net_metering_type": "NEM",
      "net_metering_note": null,
      "solar_installations": 0,
      "solar_capacity_mw": 0,
      "urdb_rate_name": "Residential Rural",
      "urdb_rate_per_kwh": 0.099,
      "updated_at": "2026-02-09"
    },
    {
      "utility_id": "3137",
      "utility_name": "Cascade Municipal Utilities",
      "state": "IA",
      "ownership_type": "municipal",
      "customer_count": 0,
      "residential_rate_per_kwh": 0.1168,
      "rate_data_source": "OpenEI_URDB",
      "rate_structure": "flat",
      "tou_available": false,
      "demand_charges": false,
      "has_net_metering": true,
      "net_metering_type": "NEM",
      "net_metering_note": null,
      "solar_installations": 0,
      "solar_capacity_mw": 0,
      "urdb_rate_name": "All Electric Rate",
      "urdb_rate_per_kwh": 0.1168,
      "updated_at": "2026-02-09"
    },
    {
      "utility_id": "3314",
      "utility_name": "Chariton Valley Elec Coop, Inc",
      "state": "IA",
      "ownership_type": "cooperative",
      "customer_count": 0,
      "residential_rate_per_kwh": 0.093,
      "rate_data_source": "OpenEI_URDB",
      "rate_structure": "flat",
      "tou_available": false,
      "demand_charges": false,
      "has_net_metering": true,
      "net_metering_type": "NEM",
      "net_metering_note": null,
      "solar_installations": 0,
      "solar_capacity_mw": 0,
      "urdb_rate_name": "Rural - 1",
      "urdb_rate_per_kwh": 0.093,
      "updated_at": "2026-02-09"
    },
    {
      "utility_id": "3722",
      "utility_name": "Clarke Electric Coop Inc",
      "state": "IA",
      "ownership_type": "cooperative",
      "customer_count": 0,
      "residential_rate_per_kwh": 0.029,
      "rate_data_source": "OpenEI_URDB",
      "rate_structure": "tou",
      "tou_available": true,
      "demand_charges": false,
      "has_net_metering": true,
      "net_metering_type": "NEM",
      "net_metering_note": null,
      "solar_installations": 0,
      "solar_capacity_mw": 0,
      "urdb_rate_name": "Electric Space Heating Rate",
      "urdb_rate_per_kwh": 0.029,
      "updated_at": "2026-02-09"
    },
    {
      "utility_id": "3900",
      "utility_name": "City of Coggon, Iowa (Utility Company)",
      "state": "IA",
      "ownership_type": "municipal",
      "customer_count": 0,
      "residential_rate_per_kwh": 0.14,
      "rate_data_source": "OpenEI_URDB",
      "rate_structure": "tiered",
      "tou_available": false,
      "demand_charges": false,
      "has_net_metering": true,
      "net_metering_type": "NEM",
      "net_metering_note": null,
      "solar_installations": 0,
      "solar_capacity_mw": 0,
      "urdb_rate_name": "Basic Electric",
      "urdb_rate_per_kwh": 0.14,
      "updated_at": "2026-02-09"
    },
    {
      "utility_id": "4304",
      "utility_name": "City of Corwith, Iowa (Utility Company)",
      "state": "IA",
      "ownership_type": "municipal",
      "customer_count": 0,
      "residential_rate_per_kwh": 0.091,
      "rate_data_source": "OpenEI_URDB",
      "rate_structure": "flat",
      "tou_available": false,
      "demand_charges": false,
      "has_net_metering": true,
      "net_metering_type": "NEM",
      "net_metering_note": null,
      "solar_installations": 0,
      "solar_capacity_mw": 0,
      "urdb_rate_name": "Residential",
      "urdb_rate_per_kwh": 0.091,
      "updated_at": "2026-02-09"
    },
    {
      "utility_id": "4305",
      "utility_name": "City of Coon Rapids, Iowa (Utility Company)",
      "state": "IA",
      "ownership_type": "municipal",
      "customer_count": 0,
      "residential_rate_per_kwh": 0.0578,
      "rate_data_source": "OpenEI_URDB",
      "rate_structure": "flat",
      "tou_available": false,
      "demand_charges": false,
      "has_net_metering": true,
      "net_metering_type": "NEM",
      "net_metering_note": null,
      "solar_installations": 0,
      "solar_capacity_mw": 0,
      "urdb_rate_name": "Residential",
      "urdb_rate_per_kwh": 0.0578,
      "updated_at": "2026-02-09"
    },
    {
      "utility_id": "4375",
      "utility_name": "City of Corning, Iowa (Utility Company)",
      "state": "IA",
      "ownership_type": "municipal",
      "customer_count": 0,
      "residential_rate_per_kwh": 0.0814,
      "rate_data_source": "OpenEI_URDB",
      "rate_structure": "flat",
      "tou_available": false,
      "demand_charges": false,
      "has_net_metering": true,
      "net_metering_type": "NEM",
      "net_metering_note": null,
      "solar_installations": 0,
      "solar_capacity_mw": 0,
      "urdb_rate_name": "Rural Residential All-Electric",
      "urdb_rate_per_kwh": 0.0814,
      "updated_at": "2026-02-09"
    },
    {
      "utility_id": "4791",
      "utility_name": "City of Danville, Iowa (Utility Company)",
      "state": "IA",
      "ownership_type": "municipal",
      "customer_count": 0,
      "residential_rate_per_kwh": 0.0748,
      "rate_data_source": "OpenEI_URDB",
      "rate_structure": "flat",
      "tou_available": false,
      "demand_charges": false,
      "has_net_metering": true,
      "net_metering_type": "NEM",
      "net_metering_note": null,
      "solar_installations": 0,
      "solar_capacity_mw": 0,
      "urdb_rate_name": "Residential All-Electric",
      "urdb_rate_per_kwh": 0.0748,
      "updated_at": "2026-02-09"
    },
    {
      "utility_id": "4919",
      "utility_name": "City of Dayton, Iowa (Utility Company)",
      "state": "IA",
      "ownership_type": "municipal",
      "customer_count": 0,
      "residential_rate_per_kwh": 0.0955,
      "rate_data_source": "OpenEI_URDB",
      "rate_structure": "tiered",
      "tou_available": false,
      "demand_charges": false,
      "has_net_metering": true,
      "net_metering_type": "NEM",
      "net_metering_note": null,
      "solar_installations": 0,
      "solar_capacity_mw": 0,
      "urdb_rate_name": "Residential",
      "urdb_rate_per_kwh": 0.0955,
      "updated_at": "2026-02-09"
    },
    {
      "utility_id": "5056",
      "utility_name": "City of Denison, Iowa (Utility Company)",
      "state": "IA",
      "ownership_type": "municipal",
      "customer_count": 0,
      "residential_rate_per_kwh": 0.0645,
      "rate_data_source": "OpenEI_URDB",
      "rate_structure": "tou",
      "tou_available": true,
      "demand_charges": false,
      "has_net_metering": true,
      "net_metering_type": "NEM",
      "net_metering_note": null,
      "solar_installations": 0,
      "solar_capacity_mw": 0,
      "urdb_rate_name": "Residential (R-1)",
      "urdb_rate_per_kwh": 0.0645,
      "updated_at": "2026-02-09"
    },
    {
      "utility_id": "5076",
      "utility_name": "City of Denver, Iowa (Utility Company)",
      "state": "IA",
      "ownership_type": "municipal",
      "customer_count": 0,
      "residential_rate_per_kwh": 0.0688,
      "rate_data_source": "OpenEI_URDB",
      "rate_structure": "tiered",
      "tou_available": false,
      "demand_charges": false,
      "has_net_metering": true,
      "net_metering_type": "NEM",
      "net_metering_note": null,
      "solar_installations": 0,
      "solar_capacity_mw": 0,
      "urdb_rate_name": "Residential",
      "urdb_rate_per_kwh": 0.0688,
      "updated_at": "2026-02-09"
    },
    {
      "utility_id": "5529",
      "utility_name": "City of Durant, Iowa (Utility Company)",
      "state": "IA",
      "ownership_type": "municipal",
      "customer_count": 0,
      "residential_rate_per_kwh": 0.115,
      "rate_data_source": "OpenEI_URDB",
      "rate_structure": "tiered",
      "tou_available": false,
      "demand_charges": false,
      "has_net_metering": true,
      "net_metering_type": "NEM",
      "net_metering_note": null,
      "solar_installations": 0,
      "solar_capacity_mw": 0,
      "urdb_rate_name": "Residential",
      "urdb_rate_per_kwh": 0.115,
      "updated_at": "2026-02-09"
    },
    {
      "utility_id": "5563",
      "utility_name": "City of Earlville, Iowa (Utility Company)",
      "state": "IA",
      "ownership_type": "municipal",
      "customer_count": 0,
      "residential_rate_per_kwh": 0.0912,
      "rate_data_source": "OpenEI_URDB",
      "rate_structure": "flat",
      "tou_available": false,
      "demand_charges": false,
      "has_net_metering": true,
      "net_metering_type": "NEM",
      "net_metering_note": null,
      "solar_installations": 0,
      "solar_capacity_mw": 0,
      "urdb_rate_name": "Residential Rate",
      "urdb_rate_per_kwh": 0.0912,
      "updated_at": "2026-02-09"
    },
    {
      "utility_id": "5742",
      "utility_name": "Eldridge City Utilities",
      "state": "IA",
      "ownership_type": "IOU",
      "customer_count": 0,
      "residential_rate_per_kwh": 0.0736,
      "rate_data_source": "OpenEI_URDB",
      "rate_structure": "tou",
      "tou_available": true,
      "demand_charges": false,
      "has_net_metering": true,
      "net_metering_type": "NEM",
      "net_metering_note": null,
      "solar_installations": 0,
      "solar_capacity_mw": 0,
      "urdb_rate_name": "Residential",
      "urdb_rate_per_kwh": 0.0736,
      "updated_at": "2026-02-09"
    },
    {
      "utility_id": "5827",
      "utility_name": "City of Ellsworth, Iowa (Utility Company)",
      "state": "IA",
      "ownership_type": "municipal",
      "customer_count": 0,
      "residential_rate_per_kwh": 0.1295,
      "rate_data_source": "OpenEI_URDB",
      "rate_structure": "tou",
      "tou_available": true,
      "demand_charges": false,
      "has_net_metering": true,
      "net_metering_type": "NEM",
      "net_metering_note": null,
      "solar_installations": 0,
      "solar_capacity_mw": 0,
      "urdb_rate_name": "Residential Electric",
      "urdb_rate_per_kwh": 0.1295,
      "updated_at": "2026-02-09"
    },
    {
      "utility_id": "5998",
      "utility_name": "City of Estherville, Iowa (Utility Company)",
      "state": "IA",
      "ownership_type": "municipal",
      "customer_count": 0,
      "residential_rate_per_kwh": 0.11,
      "rate_data_source": "OpenEI_URDB",
      "rate_structure": "flat",
      "tou_available": false,
      "demand_charges": false,
      "has_net_metering": true,
      "net_metering_type": "NEM",
      "net_metering_note": null,
      "solar_installations": 0,
      "solar_capacity_mw": 0,
      "urdb_rate_name": "RESIDENTIAL ELECTRIC",
      "urdb_rate_per_kwh": 0.11,
      "updated_at": "2026-02-09"
    },
    {
      "utility_id": "6112",
      "utility_name": "Farmers Electric Coop, Inc",
      "state": "IA",
      "ownership_type": "cooperative",
      "customer_count": 0,
      "residential_rate_per_kwh": 0.1115,
      "rate_data_source": "OpenEI_URDB",
      "rate_structure": "tiered",
      "tou_available": false,
      "demand_charges": false,
      "has_net_metering": true,
      "net_metering_type": "NEM",
      "net_metering_note": null,
      "solar_installations": 0,
      "solar_capacity_mw": 0,
      "urdb_rate_name": "Residential rate less than 100 kva",
      "urdb_rate_per_kwh": 0.1115,
      "updated_at": "2026-02-09"
    },
    {
      "utility_id": "6127",
      "utility_name": "City of Fairbank, Iowa (Utility Company)",
      "state": "IA",
      "ownership_type": "municipal",
      "customer_count": 0,
      "residential_rate_per_kwh": 0.0548,
      "rate_data_source": "OpenEI_URDB",
      "rate_structure": "tiered",
      "tou_available": false,
      "demand_charges": false,
      "has_net_metering": true,
      "net_metering_type": "NEM",
      "net_metering_note": null,
      "solar_installations": 0,
      "solar_capacity_mw": 0,
      "urdb_rate_name": "Residential- All Electric",
      "urdb_rate_per_kwh": 0.0548,
      "updated_at": "2026-02-09"
    },
    {
      "utility_id": "6168",
      "utility_name": "Farmers Electric Coop",
      "state": "IA",
      "ownership_type": "cooperative",
      "customer_count": 0,
      "residential_rate_per_kwh": 0.1157,
      "rate_data_source": "OpenEI_URDB",
      "rate_structure": "flat",
      "tou_available": false,
      "demand_charges": false,
      "has_net_metering": true,
      "net_metering_type": "NEM",
      "net_metering_note": null,
      "solar_installations": 0,
      "solar_capacity_mw": 0,
      "urdb_rate_name": "Single-Phase Residential (",
      "urdb_rate_per_kwh": 0.1157,
      "updated_at": "2026-02-09"
    },
    {
      "utility_id": "6210",
      "utility_name": "City of Farnhamville, Iowa (Utility Company)",
      "state": "IA",
      "ownership_type": "municipal",
      "customer_count": 0,
      "residential_rate_per_kwh": 0.1254,
      "rate_data_source": "OpenEI_URDB",
      "rate_structure": "tiered",
      "tou_available": false,
      "demand_charges": false,
      "has_net_metering": true,
      "net_metering_type": "NEM",
      "net_metering_note": null,
      "solar_installations": 0,
      "solar_capacity_mw": 0,
      "urdb_rate_name": "Residential",
      "urdb_rate_per_kwh": 0.1254,
      "updated_at": "2026-02-09"
    },
    {
      "utility_id": "6496",
      "utility_name": "City of Fonda, Iowa (Utility Company)",
      "state": "IA",
      "ownership_type": "municipal",
      "customer_count": 0,
      "residential_rate_per_kwh": 0.0823,
      "rate_data_source": "OpenEI_URDB",
      "rate_structure": "tiered",
      "tou_available": false,
      "demand_charges": false,
      "has_net_metering": true,
      "net_metering_type": "NEM",
      "net_metering_note": null,
      "solar_installations": 0,
      "solar_capacity_mw": 0,
      "urdb_rate_name": "Residential with Electric Water Heating",
      "urdb_rate_per_kwh": 0.0823,
      "updated_at": "2026-02-09"
    },
    {
      "utility_id": "6501",
      "utility_name": "City of Fontanelle, Iowa (Utility Company)",
      "state": "IA",
      "ownership_type": "municipal",
      "customer_count": 0,
      "residential_rate_per_kwh": 0.07,
      "rate_data_source": "OpenEI_URDB",
      "rate_structure": "flat",
      "tou_available": false,
      "demand_charges": false,
      "has_net_metering": true,
      "net_metering_type": "NEM",
      "net_metering_note": null,
      "solar_installations": 0,
      "solar_capacity_mw": 0,
      "urdb_rate_name": "Residential Rate",
      "urdb_rate_per_kwh": 0.07,
      "updated_at": "2026-02-09"
    },
    {
      "utility_id": "6579",
      "utility_name": "City of Forest City, Iowa (Utility Company)",
      "state": "IA",
      "ownership_type": "municipal",
      "customer_count": 0,
      "residential_rate_per_kwh": 0.095,
      "rate_data_source": "OpenEI_URDB",
      "rate_structure": "flat",
      "tou_available": false,
      "demand_charges": false,
      "has_net_metering": true,
      "net_metering_type": "NEM",
      "net_metering_note": null,
      "solar_installations": 0,
      "solar_capacity_mw": 0,
      "urdb_rate_name": "Residential Electric",
      "urdb_rate_per_kwh": 0.095,
      "updated_at": "2026-02-09"
    },
    {
      "utility_id": "6722",
      "utility_name": "Franklin Rural Electric Cooperative",
      "state": "IA",
      "ownership_type": "cooperative",
      "customer_count": 0,
      "residential_rate_per_kwh": 0.0613,
      "rate_data_source": "OpenEI_URDB",
      "rate_structure": "tou",
      "tou_available": true,
      "demand_charges": false,
      "has_net_metering": true,
      "net_metering_type": "NEM",
      "net_metering_note": null,
      "solar_installations": 0,
      "solar_capacity_mw": 0,
      "urdb_rate_name": "Storage Space Heating",
      "urdb_rate_per_kwh": 0.0613,
      "updated_at": "2026-02-09"
    },
    {
      "utility_id": "6759",
      "utility_name": "City of Fredericksburg, Iowa (Utility Company)",
      "state": "IA",
      "ownership_type": "municipal",
      "customer_count": 0,
      "residential_rate_per_kwh": 0.0864,
      "rate_data_source": "OpenEI_URDB",
      "rate_structure": "tou",
      "tou_available": true,
      "demand_charges": false,
      "has_net_metering": true,
      "net_metering_type": "NEM",
      "net_metering_note": null,
      "solar_installations": 0,
      "solar_capacity_mw": 0,
      "urdb_rate_name": "Electric Heat Rates",
      "urdb_rate_per_kwh": 0.0864,
      "updated_at": "2026-02-09"
    },
    {
      "utility_id": "7295",
      "utility_name": "City of Glidden, Iowa (Utility Company)",
      "state": "IA",
      "ownership_type": "municipal",
      "customer_count": 0,
      "residential_rate_per_kwh": 0.0869,
      "rate_data_source": "OpenEI_URDB",
      "rate_structure": "flat",
      "tou_available": false,
      "demand_charges": false,
      "has_net_metering": true,
      "net_metering_type": "NEM",
      "net_metering_note": null,
      "solar_installations": 0,
      "solar_capacity_mw": 0,
      "urdb_rate_name": "Residential Rate Three Phase",
      "urdb_rate_per_kwh": 0.0869,
      "updated_at": "2026-02-09"
    },
    {
      "utility_id": "7424",
      "utility_name": "Gowrie Municipal Utilities",
      "state": "IA",
      "ownership_type": "municipal",
      "customer_count": 0,
      "residential_rate_per_kwh": 0.085,
      "rate_data_source": "OpenEI_URDB",
      "rate_structure": "flat",
      "tou_available": false,
      "demand_charges": false,
      "has_net_metering": true,
      "net_metering_type": "NEM",
      "net_metering_note": null,
      "solar_installations": 0,
      "solar_capacity_mw": 0,
      "urdb_rate_name": "Residential",
      "urdb_rate_per_kwh": 0.085,
      "updated_at": "2026-02-09"
    },
    {
      "utility_id": "7443",
      "utility_name": "City of Graettinger, Iowa (Utility Company)",
      "state": "IA",
      "ownership_type": "municipal",
      "customer_count": 0,
      "residential_rate_per_kwh": 0.0778,
      "rate_data_source": "OpenEI_URDB",
      "rate_structure": "tiered",
      "tou_available": false,
      "demand_charges": false,
      "has_net_metering": true,
      "net_metering_type": "NEM",
      "net_metering_note": null,
      "solar_installations": 0,
      "solar_capacity_mw": 0,
      "urdb_rate_name": "Residential",
      "urdb_rate_per_kwh": 0.0778,
      "updated_at": "2026-02-09"
    },
    {
      "utility_id": "7486",
      "utility_name": "City of Grand Junction, Iowa (Utility Company)",
      "state": "IA",
      "ownership_type": "municipal",
      "customer_count": 0,
      "residential_rate_per_kwh": 0.1258,
      "rate_data_source": "OpenEI_URDB",
      "rate_structure": "tiered",
      "tou_available": false,
      "demand_charges": false,
      "has_net_metering": true,
      "net_metering_type": "NEM",
      "net_metering_note": null,
      "solar_installations": 0,
      "solar_capacity_mw": 0,
      "urdb_rate_name": "Residential Eletric",
      "urdb_rate_per_kwh": 0.1258,
      "updated_at": "2026-02-09"
    },
    {
      "utility_id": "7626",
      "utility_name": "City of Greenfield, Iowa (Utility Company)",
      "state": "IA",
      "ownership_type": "municipal",
      "customer_count": 0,
      "residential_rate_per_kwh": 0.063,
      "rate_data_source": "OpenEI_URDB",
      "rate_structure": "flat",
      "tou_available": false,
      "demand_charges": false,
      "has_net_metering": true,
      "net_metering_type": "NEM",
      "net_metering_note": null,
      "solar_installations": 0,
      "solar_capacity_mw": 0,
      "urdb_rate_name": "Residential Rates - Outside city limits",
      "urdb_rate_per_kwh": 0.063,
      "updated_at": "2026-02-09"
    },
    {
      "utility_id": "7743",
      "utility_name": "Grundy Center Mun Light & Power",
      "state": "IA",
      "ownership_type": "IOU",
      "customer_count": 0,
      "residential_rate_per_kwh": 0.0901,
      "rate_data_source": "OpenEI_URDB",
      "rate_structure": "tiered",
      "tou_available": false,
      "demand_charges": false,
      "has_net_metering": true,
      "net_metering_type": "NEM",
      "net_metering_note": null,
      "solar_installations": 0,
      "solar_capacity_mw": 0,
      "urdb_rate_name": "Residential Rates",
      "urdb_rate_per_kwh": 0.0901,
      "updated_at": "2026-02-09"
    },
    {
      "utility_id": "7750",
      "utility_name": "Guthrie County Rural E C A",
      "state": "IA",
      "ownership_type": "IOU",
      "customer_count": 0,
      "residential_rate_per_kwh": 0.0828,
      "rate_data_source": "OpenEI_URDB",
      "rate_structure": "flat",
      "tou_available": false,
      "demand_charges": false,
      "has_net_metering": true,
      "net_metering_type": "NEM",
      "net_metering_note": null,
      "solar_installations": 0,
      "solar_capacity_mw": 0,
      "urdb_rate_name": "Single Phase",
      "urdb_rate_per_kwh": 0.0828,
      "updated_at": "2026-02-09"
    },
    {
      "utility_id": "7837",
      "utility_name": "City of Guttenberg, Iowa (Utility Company)",
      "state": "IA",
      "ownership_type": "municipal",
      "customer_count": 0,
      "residential_rate_per_kwh": 0.112,
      "rate_data_source": "OpenEI_URDB",
      "rate_structure": "flat",
      "tou_available": false,
      "demand_charges": false,
      "has_net_metering": true,
      "net_metering_type": "NEM",
      "net_metering_note": null,
      "solar_installations": 0,
      "solar_capacity_mw": 0,
      "urdb_rate_name": "Residential customers outside the corporate limits of the City of Guttenberg",
      "urdb_rate_per_kwh": 0.112,
      "updated_at": "2026-02-09"
    },
    {
      "utility_id": "7864",
      "utility_name": "Grundy County Rural Elec Coop",
      "state": "IA",
      "ownership_type": "cooperative",
      "customer_count": 0,
      "residential_rate_per_kwh": 0.1135,
      "rate_data_source": "OpenEI_URDB",
      "rate_structure": "tiered",
      "tou_available": false,
      "demand_charges": true,
      "has_net_metering": true,
      "net_metering_type": "NEM",
      "net_metering_note": null,
      "solar_installations": 0,
      "solar_capacity_mw": 0,
      "urdb_rate_name": "Single Phase Farm and Residential",
      "urdb_rate_per_kwh": 0.1135,
      "updated_at": "2026-02-09"
    },
    {
      "utility_id": "8122",
      "utility_name": "City of Harlan, Iowa (Utility Company)",
      "state": "IA",
      "ownership_type": "municipal",
      "customer_count": 0,
      "residential_rate_per_kwh": 0.0742,
      "rate_data_source": "OpenEI_URDB",
      "rate_structure": "tou",
      "tou_available": true,
      "demand_charges": false,
      "has_net_metering": true,
      "net_metering_type": "NEM",
      "net_metering_note": null,
      "solar_installations": 0,
      "solar_capacity_mw": 0,
      "urdb_rate_name": "Residential with Electric Heat",
      "urdb_rate_per_kwh": 0.0742,
      "updated_at": "2026-02-09"
    },
    {
      "utility_id": "8214",
      "utility_name": "City of Hartley, Iowa (Utility Company)",
      "state": "IA",
      "ownership_type": "municipal",
      "customer_count": 0,
      "residential_rate_per_kwh": 0.0765,
      "rate_data_source": "OpenEI_URDB",
      "rate_structure": "flat",
      "tou_available": false,
      "demand_charges": false,
      "has_net_metering": true,
      "net_metering_type": "NEM",
      "net_metering_note": null,
      "solar_installations": 0,
      "solar_capacity_mw": 0,
      "urdb_rate_name": "Residential Service - Rural",
      "urdb_rate_per_kwh": 0.0765,
      "updated_at": "2026-02-09"
    },
    {
      "utility_id": "8288",
      "utility_name": "City of Hawarden, Iowa (Utility Company)",
      "state": "IA",
      "ownership_type": "municipal",
      "customer_count": 0,
      "residential_rate_per_kwh": 0.0755,
      "rate_data_source": "OpenEI_URDB",
      "rate_structure": "flat",
      "tou_available": false,
      "demand_charges": false,
      "has_net_metering": true,
      "net_metering_type": "NEM",
      "net_metering_note": null,
      "solar_installations": 0,
      "solar_capacity_mw": 0,
      "urdb_rate_name": "RESIDENTIAL",
      "urdb_rate_per_kwh": 0.0755,
      "updated_at": "2026-02-09"
    },
    {
      "utility_id": "8610",
      "utility_name": "City of Hinton, Iowa (Utility Company)",
      "state": "IA",
      "ownership_type": "municipal",
      "customer_count": 0,
      "residential_rate_per_kwh": 0.0132,
      "rate_data_source": "OpenEI_URDB",
      "rate_structure": "flat",
      "tou_available": false,
      "demand_charges": false,
      "has_net_metering": true,
      "net_metering_type": "NEM",
      "net_metering_note": null,
      "solar_installations": 0,
      "solar_capacity_mw": 0,
      "urdb_rate_name": "Industrial Electric Heat(Submeter)",
      "urdb_rate_per_kwh": 0.0132,
      "updated_at": "2026-02-09"
    },
    {
      "utility_id": "8847",
      "utility_name": "City of Hopkinton, Iowa (Utility Company)",
      "state": "IA",
      "ownership_type": "municipal",
      "customer_count": 0,
      "residential_rate_per_kwh": 0.115,
      "rate_data_source": "OpenEI_URDB",
      "rate_structure": "flat",
      "tou_available": false,
      "demand_charges": false,
      "has_net_metering": true,
      "net_metering_type": "NEM",
      "net_metering_note": null,
      "solar_installations": 0,
      "solar_capacity_mw": 0,
      "urdb_rate_name": "Residential",
      "urdb_rate_per_kwh": 0.115,
      "updated_at": "2026-02-09"
    },
    {
      "utility_id": "9275",
      "utility_name": "Indianola Municipal Utilities",
      "state": "IA",
      "ownership_type": "municipal",
      "customer_count": 0,
      "residential_rate_per_kwh": 0.0952,
      "rate_data_source": "OpenEI_URDB",
      "rate_structure": "tou",
      "tou_available": true,
      "demand_charges": false,
      "has_net_metering": true,
      "net_metering_type": "NEM",
      "net_metering_note": null,
      "solar_installations": 0,
      "solar_capacity_mw": 0,
      "urdb_rate_name": "Residential Rates",
      "urdb_rate_per_kwh": 0.0952,
      "updated_at": "2026-02-09"
    },
    {
      "utility_id": "10172",
      "utility_name": "City of Marathon, Iowa (Utility Company)",
      "state": "IA",
      "ownership_type": "municipal",
      "customer_count": 0,
      "residential_rate_per_kwh": 0.115,
      "rate_data_source": "OpenEI_URDB",
      "rate_structure": "tiered",
      "tou_available": false,
      "demand_charges": false,
      "has_net_metering": true,
      "net_metering_type": "NEM",
      "net_metering_note": null,
      "solar_installations": 0,
      "solar_capacity_mw": 0,
      "urdb_rate_name": "Residential",
      "urdb_rate_per_kwh": 0.115,
      "updated_at": "2026-02-09"
    },
    {
      "utility_id": "10181",
      "utility_name": "Keosauqua Municipal Light & Pwr",
      "state": "IA",
      "ownership_type": "municipal",
      "customer_count": 0,
      "residential_rate_per_kwh": 0.1116,
      "rate_data_source": "OpenEI_URDB",
      "rate_structure": "flat",
      "tou_available": false,
      "demand_charges": false,
      "has_net_metering": true,
      "net_metering_type": "NEM",
      "net_metering_note": null,
      "solar_installations": 0,
      "solar_capacity_mw": 0,
      "urdb_rate_name": "Residential",
      "urdb_rate_per_kwh": 0.1116,
      "updated_at": "2026-02-09"
    },
    {
      "utility_id": "10265",
      "utility_name": "City of Kimballton, Iowa (Utility Company)",
      "state": "IA",
      "ownership_type": "municipal",
      "customer_count": 0,
      "residential_rate_per_kwh": 0.0924,
      "rate_data_source": "OpenEI_URDB",
      "rate_structure": "tiered",
      "tou_available": false,
      "demand_charges": false,
      "has_net_metering": true,
      "net_metering_type": "NEM",
      "net_metering_note": null,
      "solar_installations": 0,
      "solar_capacity_mw": 0,
      "urdb_rate_name": "General Residential Rate",
      "urdb_rate_per_kwh": 0.0924,
      "updated_at": "2026-02-09"
    },
    {
      "utility_id": "10542",
      "utility_name": "La Porte City Utilities",
      "state": "IA",
      "ownership_type": "IOU",
      "customer_count": 0,
      "residential_rate_per_kwh": 0.1017,
      "rate_data_source": "OpenEI_URDB",
      "rate_structure": "tiered",
      "tou_available": false,
      "demand_charges": false,
      "has_net_metering": true,
      "net_metering_type": "NEM",
      "net_metering_note": null,
      "solar_installations": 0,
      "solar_capacity_mw": 0,
      "urdb_rate_name": "Residential Electric Service Charge",
      "urdb_rate_per_kwh": 0.1017,
      "updated_at": "2026-02-09"
    },
    {
      "utility_id": "10606",
      "utility_name": "City of Lake Mills, Iowa (Utility Company)",
      "state": "IA",
      "ownership_type": "municipal",
      "customer_count": 0,
      "residential_rate_per_kwh": 0.1104,
      "rate_data_source": "OpenEI_URDB",
      "rate_structure": "flat",
      "tou_available": false,
      "demand_charges": false,
      "has_net_metering": true,
      "net_metering_type": "NEM",
      "net_metering_note": null,
      "solar_installations": 0,
      "solar_capacity_mw": 0,
      "urdb_rate_name": "Residential",
      "urdb_rate_per_kwh": 0.1104,
      "updated_at": "2026-02-09"
    },
    {
      "utility_id": "10608",
      "utility_name": "City of Lake Park, Iowa (Utility Company)",
      "state": "IA",
      "ownership_type": "municipal",
      "customer_count": 0,
      "residential_rate_per_kwh": 0.1067,
      "rate_data_source": "OpenEI_URDB",
      "rate_structure": "tou",
      "tou_available": true,
      "demand_charges": false,
      "has_net_metering": true,
      "net_metering_type": "NEM",
      "net_metering_note": null,
      "solar_installations": 0,
      "solar_capacity_mw": 0,
      "urdb_rate_name": "Seasonal",
      "urdb_rate_per_kwh": 0.1067,
      "updated_at": "2026-02-09"
    },
    {
      "utility_id": "10617",
      "utility_name": "City of Lake View, Iowa (Utility Company)",
      "state": "IA",
      "ownership_type": "municipal",
      "customer_count": 0,
      "residential_rate_per_kwh": 0.0745,
      "rate_data_source": "OpenEI_URDB",
      "rate_structure": "tiered",
      "tou_available": false,
      "demand_charges": false,
      "has_net_metering": true,
      "net_metering_type": "NEM",
      "net_metering_note": null,
      "solar_installations": 0,
      "solar_capacity_mw": 0,
      "urdb_rate_name": "Rural Service",
      "urdb_rate_per_kwh": 0.0745,
      "updated_at": "2026-02-09"
    },
    {
      "utility_id": "10650",
      "utility_name": "City of Lamoni, Iowa (Utility Company)",
      "state": "IA",
      "ownership_type": "municipal",
      "customer_count": 0,
      "residential_rate_per_kwh": 0.0861,
      "rate_data_source": "OpenEI_URDB",
      "rate_structure": "tiered",
      "tou_available": false,
      "demand_charges": false,
      "has_net_metering": true,
      "net_metering_type": "NEM",
      "net_metering_note": null,
      "solar_installations": 0,
      "solar_capacity_mw": 0,
      "urdb_rate_name": "Residential Electric Rate",
      "urdb_rate_per_kwh": 0.0861,
      "updated_at": "2026-02-09"
    },
    {
      "utility_id": "10706",
      "utility_name": "City of Larchwood, Iowa (Utility Company)",
      "state": "IA",
      "ownership_type": "municipal",
      "customer_count": 0,
      "residential_rate_per_kwh": 0.0811,
      "rate_data_source": "OpenEI_URDB",
      "rate_structure": "flat",
      "tou_available": false,
      "demand_charges": false,
      "has_net_metering": true,
      "net_metering_type": "NEM",
      "net_metering_note": null,
      "solar_installations": 0,
      "solar_capacity_mw": 0,
      "urdb_rate_name": "Residential Electric Rate",
      "urdb_rate_per_kwh": 0.0811,
      "updated_at": "2026-02-09"
    },
    {
      "utility_id": "10769",
      "utility_name": "City of Laurens, Iowa (Utility Company)",
      "state": "IA",
      "ownership_type": "municipal",
      "customer_count": 0,
      "residential_rate_per_kwh": 0.0711,
      "rate_data_source": "OpenEI_URDB",
      "rate_structure": "flat",
      "tou_available": false,
      "demand_charges": false,
      "has_net_metering": true,
      "net_metering_type": "NEM",
      "net_metering_note": null,
      "solar_installations": 0,
      "solar_capacity_mw": 0,
      "urdb_rate_name": "Residential Rate",
      "urdb_rate_per_kwh": 0.0711,
      "updated_at": "2026-02-09"
    },
    {
      "utility_id": "10784",
      "utility_name": "City of Lawler, Iowa (Utility Company)",
      "state": "IA",
      "ownership_type": "municipal",
      "customer_count": 0,
      "residential_rate_per_kwh": 0.1063,
      "rate_data_source": "OpenEI_URDB",
      "rate_structure": "tiered",
      "tou_available": false,
      "demand_charges": false,
      "has_net_metering": true,
      "net_metering_type": "NEM",
      "net_metering_note": null,
      "solar_installations": 0,
      "solar_capacity_mw": 0,
      "urdb_rate_name": "Residential",
      "urdb_rate_per_kwh": 0.1063,
      "updated_at": "2026-02-09"
    },
    {
      "utility_id": "10881",
      "utility_name": "City of Lehigh, Iowa (Utility Company)",
      "state": "IA",
      "ownership_type": "municipal",
      "customer_count": 0,
      "residential_rate_per_kwh": 0.0594,
      "rate_data_source": "OpenEI_URDB",
      "rate_structure": "tiered",
      "tou_available": false,
      "demand_charges": false,
      "has_net_metering": true,
      "net_metering_type": "NEM",
      "net_metering_note": null,
      "solar_installations": 0,
      "solar_capacity_mw": 0,
      "urdb_rate_name": "Residential",
      "urdb_rate_per_kwh": 0.0594,
      "updated_at": "2026-02-09"
    },
    {
      "utility_id": "10908",
      "utility_name": "City of Lenox, Iowa (Utility Company)",
      "state": "IA",
      "ownership_type": "municipal",
      "customer_count": 0,
      "residential_rate_per_kwh": 0.065,
      "rate_data_source": "OpenEI_URDB",
      "rate_structure": "tiered",
      "tou_available": false,
      "demand_charges": false,
      "has_net_metering": true,
      "net_metering_type": "NEM",
      "net_metering_note": null,
      "solar_installations": 0,
      "solar_capacity_mw": 0,
      "urdb_rate_name": "Residential Rate # 1",
      "urdb_rate_per_kwh": 0.065,
      "updated_at": "2026-02-09"
    },
    {
      "utility_id": "11093",
      "utility_name": "City of Livermore, Iowa (Utility Company)",
      "state": "IA",
      "ownership_type": "municipal",
      "customer_count": 0,
      "residential_rate_per_kwh": 0.0895,
      "rate_data_source": "OpenEI_URDB",
      "rate_structure": "tou",
      "tou_available": true,
      "demand_charges": false,
      "has_net_metering": true,
      "net_metering_type": "NEM",
      "net_metering_note": null,
      "solar_installations": 0,
      "solar_capacity_mw": 0,
      "urdb_rate_name": "Residential",
      "urdb_rate_per_kwh": 0.0895,
      "updated_at": "2026-02-09"
    },
    {
      "utility_id": "11141",
      "utility_name": "City of Long Grove, Iowa (Utility Company)",
      "state": "IA",
      "ownership_type": "municipal",
      "customer_count": 0,
      "residential_rate_per_kwh": 0.1015,
      "rate_data_source": "OpenEI_URDB",
      "rate_structure": "tou",
      "tou_available": true,
      "demand_charges": false,
      "has_net_metering": true,
      "net_metering_type": "NEM",
      "net_metering_note": null,
      "solar_installations": 0,
      "solar_capacity_mw": 0,
      "urdb_rate_name": "Residential",
      "urdb_rate_per_kwh": 0.1015,
      "updated_at": "2026-02-09"
    },
    {
      "utility_id": "11298",
      "utility_name": "Lyon Rural Electric Coop",
      "state": "IA",
      "ownership_type": "cooperative",
      "customer_count": 0,
      "residential_rate_per_kwh": 0.0707,
      "rate_data_source": "OpenEI_URDB",
      "rate_structure": "tiered",
      "tou_available": false,
      "demand_charges": false,
      "has_net_metering": true,
      "net_metering_type": "NEM",
      "net_metering_note": null,
      "solar_installations": 0,
      "solar_capacity_mw": 0,
      "urdb_rate_name": "Residential and Farm",
      "urdb_rate_per_kwh": 0.0707,
      "updated_at": "2026-02-09"
    },
    {
      "utility_id": "11568",
      "utility_name": "Town of Manilla, Iowa (Utility Company)",
      "state": "IA",
      "ownership_type": "municipal",
      "customer_count": 0,
      "residential_rate_per_kwh": 0.0712,
      "rate_data_source": "OpenEI_URDB",
      "rate_structure": "tou",
      "tou_available": true,
      "demand_charges": false,
      "has_net_metering": true,
      "net_metering_type": "NEM",
      "net_metering_note": null,
      "solar_installations": 0,
      "solar_capacity_mw": 0,
      "urdb_rate_name": "Residential-Rural",
      "urdb_rate_per_kwh": 0.0712,
      "updated_at": "2026-02-09"
    },
    {
      "utility_id": "11581",
      "utility_name": "City of Manning, Iowa (Utility Company)",
      "state": "IA",
      "ownership_type": "municipal",
      "customer_count": 0,
      "residential_rate_per_kwh": 0.082,
      "rate_data_source": "OpenEI_URDB",
      "rate_structure": "flat",
      "tou_available": false,
      "demand_charges": false,
      "has_net_metering": true,
      "net_metering_type": "NEM",
      "net_metering_note": null,
      "solar_installations": 0,
      "solar_capacity_mw": 0,
      "urdb_rate_name": "Residential Service",
      "urdb_rate_per_kwh": 0.082,
      "updated_at": "2026-02-09"
    },
    {
      "utility_id": "11609",
      "utility_name": "City of Mapleton, Iowa (Utility Company)",
      "state": "IA",
      "ownership_type": "municipal",
      "customer_count": 0,
      "residential_rate_per_kwh": 0.093,
      "rate_data_source": "OpenEI_URDB",
      "rate_structure": "flat",
      "tou_available": false,
      "demand_charges": false,
      "has_net_metering": true,
      "net_metering_type": "NEM",
      "net_metering_note": null,
      "solar_installations": 0,
      "solar_capacity_mw": 0,
      "urdb_rate_name": "11-Residential Rate",
      "urdb_rate_per_kwh": 0.093,
      "updated_at": "2026-02-09"
    },
    {
      "utility_id": "12114",
      "utility_name": "City of McGregor, Iowa (Utility Company)",
      "state": "IA",
      "ownership_type": "municipal",
      "customer_count": 0,
      "residential_rate_per_kwh": 0.1026,
      "rate_data_source": "OpenEI_URDB",
      "rate_structure": "flat",
      "tou_available": false,
      "demand_charges": false,
      "has_net_metering": true,
      "net_metering_type": "NEM",
      "net_metering_note": null,
      "solar_installations": 0,
      "solar_capacity_mw": 0,
      "urdb_rate_name": "Residential Rate",
      "urdb_rate_per_kwh": 0.1026,
      "updated_at": "2026-02-09"
    },
    {
      "utility_id": "12541",
      "utility_name": "City of Milford, Iowa (Utility Company)",
      "state": "IA",
      "ownership_type": "municipal",
      "customer_count": 0,
      "residential_rate_per_kwh": 0.086,
      "rate_data_source": "OpenEI_URDB",
      "rate_structure": "tiered",
      "tou_available": false,
      "demand_charges": false,
      "has_net_metering": true,
      "net_metering_type": "NEM",
      "net_metering_note": null,
      "solar_installations": 0,
      "solar_capacity_mw": 0,
      "urdb_rate_name": "RESIDENTIAL RATES",
      "urdb_rate_per_kwh": 0.086,
      "updated_at": "2026-02-09"
    },
    {
      "utility_id": "12839",
      "utility_name": "City of Montezuma, Iowa (Utility Company)",
      "state": "IA",
      "ownership_type": "municipal",
      "customer_count": 0,
      "residential_rate_per_kwh": 0.0907,
      "rate_data_source": "OpenEI_URDB",
      "rate_structure": "tou",
      "tou_available": true,
      "demand_charges": false,
      "has_net_metering": true,
      "net_metering_type": "NEM",
      "net_metering_note": null,
      "solar_installations": 0,
      "solar_capacity_mw": 0,
      "urdb_rate_name": "Residential Rate- Electric Heat plus other Loads",
      "urdb_rate_per_kwh": 0.0907,
      "updated_at": "2026-02-09"
    },
    {
      "utility_id": "13038",
      "utility_name": "City of Mt Pleasant, Iowa (Utility Company)",
      "state": "IA",
      "ownership_type": "municipal",
      "customer_count": 0,
      "residential_rate_per_kwh": 0.133,
      "rate_data_source": "OpenEI_URDB",
      "rate_structure": "tiered",
      "tou_available": false,
      "demand_charges": false,
      "has_net_metering": true,
      "net_metering_type": "NEM",
      "net_metering_note": null,
      "solar_installations": 0,
      "solar_capacity_mw": 0,
      "urdb_rate_name": "Residential Electric Heat - One Meter Service",
      "urdb_rate_per_kwh": 0.133,
      "updated_at": "2026-02-09"
    },
    {
      "utility_id": "13382",
      "utility_name": "City of Neola, Iowa (Utility Company)",
      "state": "IA",
      "ownership_type": "municipal",
      "customer_count": 0,
      "residential_rate_per_kwh": 0,
      "rate_data_source": "OpenEI_URDB",
      "rate_structure": "flat",
      "tou_available": false,
      "demand_charges": true,
      "has_net_metering": true,
      "net_metering_type": "NEM",
      "net_metering_note": null,
      "solar_installations": 0,
      "solar_capacity_mw": 0,
      "urdb_rate_name": "Rate Schedule Residential",
      "urdb_rate_per_kwh": null,
      "updated_at": "2026-02-09"
    },
    {
      "utility_id": "13444",
      "utility_name": "City of New Hampton, Iowa (Utility Company)",
      "state": "IA",
      "ownership_type": "municipal",
      "customer_count": 0,
      "residential_rate_per_kwh": 0.0756,
      "rate_data_source": "OpenEI_URDB",
      "rate_structure": "tiered",
      "tou_available": false,
      "demand_charges": false,
      "has_net_metering": true,
      "net_metering_type": "NEM",
      "net_metering_note": null,
      "solar_installations": 0,
      "solar_capacity_mw": 0,
      "urdb_rate_name": "All Electrical Residential Rate",
      "urdb_rate_per_kwh": 0.0756,
      "updated_at": "2026-02-09"
    },
    {
      "utility_id": "13468",
      "utility_name": "New London Municipal Utilities",
      "state": "IA",
      "ownership_type": "municipal",
      "customer_count": 0,
      "residential_rate_per_kwh": 0.1041,
      "rate_data_source": "OpenEI_URDB",
      "rate_structure": "flat",
      "tou_available": false,
      "demand_charges": false,
      "has_net_metering": true,
      "net_metering_type": "NEM",
      "net_metering_note": null,
      "solar_installations": 0,
      "solar_capacity_mw": 0,
      "urdb_rate_name": "City Residential",
      "urdb_rate_per_kwh": 0.1041,
      "updated_at": "2026-02-09"
    },
    {
      "utility_id": "13675",
      "utility_name": "Nishnabotna Valley R E C",
      "state": "IA",
      "ownership_type": "IOU",
      "customer_count": 0,
      "residential_rate_per_kwh": 0.0458,
      "rate_data_source": "OpenEI_URDB",
      "rate_structure": "flat",
      "tou_available": false,
      "demand_charges": false,
      "has_net_metering": true,
      "net_metering_type": "NEM",
      "net_metering_note": null,
      "solar_installations": 0,
      "solar_capacity_mw": 0,
      "urdb_rate_name": "Controlled Off-Peak Interruptible Heat",
      "urdb_rate_per_kwh": 0.0458,
      "updated_at": "2026-02-09"
    },
    {
      "utility_id": "13990",
      "utility_name": "City of Ogden, Iowa (Utility Company)",
      "state": "IA",
      "ownership_type": "municipal",
      "customer_count": 0,
      "residential_rate_per_kwh": 0.069,
      "rate_data_source": "OpenEI_URDB",
      "rate_structure": "tiered",
      "tou_available": false,
      "demand_charges": false,
      "has_net_metering": true,
      "net_metering_type": "NEM",
      "net_metering_note": null,
      "solar_installations": 0,
      "solar_capacity_mw": 0,
      "urdb_rate_name": "Residential Rate",
      "urdb_rate_per_kwh": 0.069,
      "updated_at": "2026-02-09"
    },
    {
      "utility_id": "14132",
      "utility_name": "City of Onawa, Iowa (Utility Company)",
      "state": "IA",
      "ownership_type": "municipal",
      "customer_count": 0,
      "residential_rate_per_kwh": 0.095,
      "rate_data_source": "OpenEI_URDB",
      "rate_structure": "flat",
      "tou_available": false,
      "demand_charges": false,
      "has_net_metering": true,
      "net_metering_type": "NEM",
      "net_metering_note": null,
      "solar_installations": 0,
      "solar_capacity_mw": 0,
      "urdb_rate_name": "Residential Service (Dual Meter)",
      "urdb_rate_per_kwh": 0.095,
      "updated_at": "2026-02-09"
    },
    {
      "utility_id": "14159",
      "utility_name": "City of Orange City, Iowa (Utility Company)",
      "state": "IA",
      "ownership_type": "municipal",
      "customer_count": 0,
      "residential_rate_per_kwh": 0.0757,
      "rate_data_source": "OpenEI_URDB",
      "rate_structure": "tou",
      "tou_available": true,
      "demand_charges": false,
      "has_net_metering": true,
      "net_metering_type": "NEM",
      "net_metering_note": null,
      "solar_installations": 0,
      "solar_capacity_mw": 0,
      "urdb_rate_name": "Residential Rate",
      "urdb_rate_per_kwh": 0.0757,
      "updated_at": "2026-02-09"
    },
    {
      "utility_id": "14166",
      "utility_name": "City of Orient, Iowa (Utility Company)",
      "state": "IA",
      "ownership_type": "municipal",
      "customer_count": 0,
      "residential_rate_per_kwh": 0.0815,
      "rate_data_source": "OpenEI_URDB",
      "rate_structure": "tiered",
      "tou_available": false,
      "demand_charges": false,
      "has_net_metering": true,
      "net_metering_type": "NEM",
      "net_metering_note": null,
      "solar_installations": 0,
      "solar_capacity_mw": 0,
      "urdb_rate_name": "Residential All-Electric",
      "urdb_rate_per_kwh": 0.0815,
      "updated_at": "2026-02-09"
    },
    {
      "utility_id": "14201",
      "utility_name": "City of Osage, Iowa (Utility Company)",
      "state": "IA",
      "ownership_type": "municipal",
      "customer_count": 0,
      "residential_rate_per_kwh": 0.0868,
      "rate_data_source": "OpenEI_URDB",
      "rate_structure": "flat",
      "tou_available": false,
      "demand_charges": false,
      "has_net_metering": true,
      "net_metering_type": "NEM",
      "net_metering_note": null,
      "solar_installations": 0,
      "solar_capacity_mw": 0,
      "urdb_rate_name": "Residential",
      "urdb_rate_per_kwh": 0.0868,
      "updated_at": "2026-02-09"
    },
    {
      "utility_id": "14202",
      "utility_name": "Osceola Electric Coop, Inc",
      "state": "IA",
      "ownership_type": "cooperative",
      "customer_count": 0,
      "residential_rate_per_kwh": 0.059,
      "rate_data_source": "OpenEI_URDB",
      "rate_structure": "flat",
      "tou_available": false,
      "demand_charges": false,
      "has_net_metering": true,
      "net_metering_type": "NEM",
      "net_metering_note": null,
      "solar_installations": 0,
      "solar_capacity_mw": 0,
      "urdb_rate_name": "Residential Electric Heat",
      "urdb_rate_per_kwh": 0.059,
      "updated_at": "2026-02-09"
    },
    {
      "utility_id": "14433",
      "utility_name": "City of Panora, Iowa (Utility Company)",
      "state": "IA",
      "ownership_type": "municipal",
      "customer_count": 0,
      "residential_rate_per_kwh": 0.0752,
      "rate_data_source": "OpenEI_URDB",
      "rate_structure": "flat",
      "tou_available": false,
      "demand_charges": false,
      "has_net_metering": true,
      "net_metering_type": "NEM",
      "net_metering_note": null,
      "solar_installations": 0,
      "solar_capacity_mw": 0,
      "urdb_rate_name": "Residential-Regular Rate",
      "urdb_rate_per_kwh": 0.0752,
      "updated_at": "2026-02-09"
    },
    {
      "utility_id": "14473",
      "utility_name": "City of Paton, Iowa (Utility Company)",
      "state": "IA",
      "ownership_type": "municipal",
      "customer_count": 0,
      "residential_rate_per_kwh": 0.0935,
      "rate_data_source": "OpenEI_URDB",
      "rate_structure": "flat",
      "tou_available": false,
      "demand_charges": false,
      "has_net_metering": true,
      "net_metering_type": "NEM",
      "net_metering_note": null,
      "solar_installations": 0,
      "solar_capacity_mw": 0,
      "urdb_rate_name": "Residential Electric",
      "urdb_rate_per_kwh": 0.0935,
      "updated_at": "2026-02-09"
    },
    {
      "utility_id": "14645",
      "utility_name": "City of Pella, Iowa (Utility Company)",
      "state": "IA",
      "ownership_type": "municipal",
      "customer_count": 0,
      "residential_rate_per_kwh": 0.105,
      "rate_data_source": "OpenEI_URDB",
      "rate_structure": "tou",
      "tou_available": true,
      "demand_charges": false,
      "has_net_metering": true,
      "net_metering_type": "NEM",
      "net_metering_note": null,
      "solar_installations": 0,
      "solar_capacity_mw": 0,
      "urdb_rate_name": "Rural Residents and Farm",
      "urdb_rate_per_kwh": 0.105,
      "updated_at": "2026-02-09"
    },
    {
      "utility_id": "15180",
      "utility_name": "City of Pocahontas, Iowa (Utility Company)",
      "state": "IA",
      "ownership_type": "municipal",
      "customer_count": 0,
      "residential_rate_per_kwh": 0.0777,
      "rate_data_source": "OpenEI_URDB",
      "rate_structure": "tou",
      "tou_available": true,
      "demand_charges": false,
      "has_net_metering": true,
      "net_metering_type": "NEM",
      "net_metering_note": null,
      "solar_installations": 0,
      "solar_capacity_mw": 0,
      "urdb_rate_name": "Residential Rates",
      "urdb_rate_per_kwh": 0.0777,
      "updated_at": "2026-02-09"
    },
    {
      "utility_id": "15377",
      "utility_name": "City of Primghar, Iowa (Utility Company)",
      "state": "IA",
      "ownership_type": "municipal",
      "customer_count": 0,
      "residential_rate_per_kwh": 0.1383,
      "rate_data_source": "OpenEI_URDB",
      "rate_structure": "tou",
      "tou_available": true,
      "demand_charges": false,
      "has_net_metering": true,
      "net_metering_type": "NEM",
      "net_metering_note": null,
      "solar_installations": 0,
      "solar_capacity_mw": 0,
      "urdb_rate_name": "Residential Rates",
      "urdb_rate_per_kwh": 0.1383,
      "updated_at": "2026-02-09"
    },
    {
      "utility_id": "15751",
      "utility_name": "City of Readlyn, Iowa (Utility Company)",
      "state": "IA",
      "ownership_type": "municipal",
      "customer_count": 0,
      "residential_rate_per_kwh": 0.118,
      "rate_data_source": "OpenEI_URDB",
      "rate_structure": "tiered",
      "tou_available": false,
      "demand_charges": false,
      "has_net_metering": true,
      "net_metering_type": "NEM",
      "net_metering_note": null,
      "solar_installations": 0,
      "solar_capacity_mw": 0,
      "urdb_rate_name": "Residential Rate",
      "urdb_rate_per_kwh": 0.118,
      "updated_at": "2026-02-09"
    },
    {
      "utility_id": "15846",
      "utility_name": "City of Remsen, Iowa (Utility Company)",
      "state": "IA",
      "ownership_type": "municipal",
      "customer_count": 0,
      "residential_rate_per_kwh": 0.3767,
      "rate_data_source": "OpenEI_URDB",
      "rate_structure": "tiered",
      "tou_available": false,
      "demand_charges": false,
      "has_net_metering": true,
      "net_metering_type": "NEM",
      "net_metering_note": null,
      "solar_installations": 0,
      "solar_capacity_mw": 0,
      "urdb_rate_name": "Residential Electric",
      "urdb_rate_per_kwh": 0.3767,
      "updated_at": "2026-02-09"
    },
    {
      "utility_id": "15862",
      "utility_name": "City of Renwick, Iowa (Utility Company)",
      "state": "IA",
      "ownership_type": "municipal",
      "customer_count": 0,
      "residential_rate_per_kwh": 0.102,
      "rate_data_source": "OpenEI_URDB",
      "rate_structure": "flat",
      "tou_available": false,
      "demand_charges": false,
      "has_net_metering": true,
      "net_metering_type": "NEM",
      "net_metering_note": null,
      "solar_installations": 0,
      "solar_capacity_mw": 0,
      "urdb_rate_name": "Residential",
      "urdb_rate_per_kwh": 0.102,
      "updated_at": "2026-02-09"
    },
    {
      "utility_id": "16206",
      "utility_name": "Rock Rapids Municipal Utility",
      "state": "IA",
      "ownership_type": "municipal",
      "customer_count": 0,
      "residential_rate_per_kwh": 0.0795,
      "rate_data_source": "OpenEI_URDB",
      "rate_structure": "tou",
      "tou_available": true,
      "demand_charges": false,
      "has_net_metering": true,
      "net_metering_type": "NEM",
      "net_metering_note": null,
      "solar_installations": 0,
      "solar_capacity_mw": 0,
      "urdb_rate_name": "Residential Power",
      "urdb_rate_per_kwh": 0.0795,
      "updated_at": "2026-02-09"
    },
    {
      "utility_id": "16211",
      "utility_name": "City of Rockford, Iowa (Utility Company)",
      "state": "IA",
      "ownership_type": "municipal",
      "customer_count": 0,
      "residential_rate_per_kwh": 0.1064,
      "rate_data_source": "OpenEI_URDB",
      "rate_structure": "tou",
      "tou_available": true,
      "demand_charges": false,
      "has_net_metering": true,
      "net_metering_type": "NEM",
      "net_metering_note": null,
      "solar_installations": 0,
      "solar_capacity_mw": 0,
      "urdb_rate_name": "Residential",
      "urdb_rate_per_kwh": 0.1064,
      "updated_at": "2026-02-09"
    },
    {
      "utility_id": "16528",
      "utility_name": "City of Sabula, Iowa (Utility Company)",
      "state": "IA",
      "ownership_type": "municipal",
      "customer_count": 0,
      "residential_rate_per_kwh": 0.06,
      "rate_data_source": "OpenEI_URDB",
      "rate_structure": "flat",
      "tou_available": false,
      "demand_charges": false,
      "has_net_metering": true,
      "net_metering_type": "NEM",
      "net_metering_note": null,
      "solar_installations": 0,
      "solar_capacity_mw": 0,
      "urdb_rate_name": "General Rate",
      "urdb_rate_per_kwh": 0.06,
      "updated_at": "2026-02-09"
    },
    {
      "utility_id": "16628",
      "utility_name": "City of Sanborn, Iowa (Utility Company)",
      "state": "IA",
      "ownership_type": "municipal",
      "customer_count": 0,
      "residential_rate_per_kwh": 0.1393,
      "rate_data_source": "OpenEI_URDB",
      "rate_structure": "tou",
      "tou_available": true,
      "demand_charges": false,
      "has_net_metering": true,
      "net_metering_type": "NEM",
      "net_metering_note": null,
      "solar_installations": 0,
      "solar_capacity_mw": 0,
      "urdb_rate_name": "Residential Rate",
      "urdb_rate_per_kwh": 0.1393,
      "updated_at": "2026-02-09"
    },
    {
      "utility_id": "16932",
      "utility_name": "City of Sergeant Bluff, Iowa (Utility Company)",
      "state": "IA",
      "ownership_type": "municipal",
      "customer_count": 0,
      "residential_rate_per_kwh": 0.0692,
      "rate_data_source": "OpenEI_URDB",
      "rate_structure": "tou",
      "tou_available": true,
      "demand_charges": false,
      "has_net_metering": true,
      "net_metering_type": "NEM",
      "net_metering_note": null,
      "solar_installations": 0,
      "solar_capacity_mw": 0,
      "urdb_rate_name": "Residential",
      "urdb_rate_per_kwh": 0.0692,
      "updated_at": "2026-02-09"
    },
    {
      "utility_id": "16992",
      "utility_name": "City of Stanton, Iowa (Utility Company)",
      "state": "IA",
      "ownership_type": "municipal",
      "customer_count": 0,
      "residential_rate_per_kwh": 0.1935,
      "rate_data_source": "OpenEI_URDB",
      "rate_structure": "tiered",
      "tou_available": false,
      "demand_charges": false,
      "has_net_metering": true,
      "net_metering_type": "NEM",
      "net_metering_note": null,
      "solar_installations": 0,
      "solar_capacity_mw": 0,
      "urdb_rate_name": "\"A1\" Single Phase Service 0-50 kVA",
      "urdb_rate_per_kwh": 0.1935,
      "updated_at": "2026-02-09"
    },
    {
      "utility_id": "17046",
      "utility_name": "City of Shelby, Iowa (Utility Company)",
      "state": "IA",
      "ownership_type": "municipal",
      "customer_count": 0,
      "residential_rate_per_kwh": 0.0923,
      "rate_data_source": "OpenEI_URDB",
      "rate_structure": "tou",
      "tou_available": true,
      "demand_charges": false,
      "has_net_metering": true,
      "net_metering_type": "NEM",
      "net_metering_note": null,
      "solar_installations": 0,
      "solar_capacity_mw": 0,
      "urdb_rate_name": "Residential Rate",
      "urdb_rate_per_kwh": 0.0923,
      "updated_at": "2026-02-09"
    },
    {
      "utility_id": "17141",
      "utility_name": "City of Sibley, Iowa (Utility Company)",
      "state": "IA",
      "ownership_type": "municipal",
      "customer_count": 0,
      "residential_rate_per_kwh": 0.069,
      "rate_data_source": "OpenEI_URDB",
      "rate_structure": "flat",
      "tou_available": false,
      "demand_charges": false,
      "has_net_metering": true,
      "net_metering_type": "NEM",
      "net_metering_note": null,
      "solar_installations": 0,
      "solar_capacity_mw": 0,
      "urdb_rate_name": "Residential",
      "urdb_rate_per_kwh": 0.069,
      "updated_at": "2026-02-09"
    },
    {
      "utility_id": "17264",
      "utility_name": "City of Sioux Center, Iowa (Utility Company)",
      "state": "IA",
      "ownership_type": "municipal",
      "customer_count": 0,
      "residential_rate_per_kwh": 0.0949,
      "rate_data_source": "OpenEI_URDB",
      "rate_structure": "flat",
      "tou_available": false,
      "demand_charges": false,
      "has_net_metering": true,
      "net_metering_type": "NEM",
      "net_metering_note": null,
      "solar_installations": 0,
      "solar_capacity_mw": 0,
      "urdb_rate_name": "Residential Rate",
      "urdb_rate_per_kwh": 0.0949,
      "updated_at": "2026-02-09"
    },
    {
      "utility_id": "17643",
      "utility_name": "Southern Iowa Elec Coop, Inc",
      "state": "IA",
      "ownership_type": "cooperative",
      "customer_count": 0,
      "residential_rate_per_kwh": 0.1121,
      "rate_data_source": "OpenEI_URDB",
      "rate_structure": "flat",
      "tou_available": false,
      "demand_charges": false,
      "has_net_metering": true,
      "net_metering_type": "NEM",
      "net_metering_note": null,
      "solar_installations": 0,
      "solar_capacity_mw": 0,
      "urdb_rate_name": "Residentail Rate",
      "urdb_rate_per_kwh": 0.1121,
      "updated_at": "2026-02-09"
    },
    {
      "utility_id": "17783",
      "utility_name": "City of Spencer, Iowa (Utility Company)",
      "state": "IA",
      "ownership_type": "municipal",
      "customer_count": 0,
      "residential_rate_per_kwh": 0.0509,
      "rate_data_source": "OpenEI_URDB",
      "rate_structure": "tiered",
      "tou_available": false,
      "demand_charges": false,
      "has_net_metering": true,
      "net_metering_type": "NEM",
      "net_metering_note": null,
      "solar_installations": 0,
      "solar_capacity_mw": 0,
      "urdb_rate_name": "Residential",
      "urdb_rate_per_kwh": 0.0509,
      "updated_at": "2026-02-09"
    },
    {
      "utility_id": "18014",
      "utility_name": "City of State Center, Iowa (Utility Company)",
      "state": "IA",
      "ownership_type": "municipal",
      "customer_count": 0,
      "residential_rate_per_kwh": 0.1207,
      "rate_data_source": "OpenEI_URDB",
      "rate_structure": "tiered",
      "tou_available": false,
      "demand_charges": false,
      "has_net_metering": true,
      "net_metering_type": "NEM",
      "net_metering_note": null,
      "solar_installations": 0,
      "solar_capacity_mw": 0,
      "urdb_rate_name": "Residential Rural",
      "urdb_rate_per_kwh": 0.1207,
      "updated_at": "2026-02-09"
    },
    {
      "utility_id": "18177",
      "utility_name": "City of Story City, Iowa (Utility Company)",
      "state": "IA",
      "ownership_type": "municipal",
      "customer_count": 0,
      "residential_rate_per_kwh": 0.0741,
      "rate_data_source": "OpenEI_URDB",
      "rate_structure": "tiered",
      "tou_available": false,
      "demand_charges": false,
      "has_net_metering": true,
      "net_metering_type": "NEM",
      "net_metering_note": null,
      "solar_installations": 0,
      "solar_capacity_mw": 0,
      "urdb_rate_name": "Residential City",
      "urdb_rate_per_kwh": 0.0741,
      "updated_at": "2026-02-09"
    },
    {
      "utility_id": "18201",
      "utility_name": "City of Stratford, Iowa (Utility Company)",
      "state": "IA",
      "ownership_type": "municipal",
      "customer_count": 0,
      "residential_rate_per_kwh": 0,
      "rate_data_source": "OpenEI_URDB",
      "rate_structure": "flat",
      "tou_available": false,
      "demand_charges": false,
      "has_net_metering": true,
      "net_metering_type": "NEM",
      "net_metering_note": null,
      "solar_installations": 0,
      "solar_capacity_mw": 0,
      "urdb_rate_name": "Seasonal Electric Heat Rate",
      "urdb_rate_per_kwh": null,
      "updated_at": "2026-02-09"
    },
    {
      "utility_id": "18204",
      "utility_name": "City of Strawberry Point, Iowa (Utility Company)",
      "state": "IA",
      "ownership_type": "municipal",
      "customer_count": 0,
      "residential_rate_per_kwh": 0.1267,
      "rate_data_source": "OpenEI_URDB",
      "rate_structure": "tou",
      "tou_available": true,
      "demand_charges": false,
      "has_net_metering": true,
      "net_metering_type": "NEM",
      "net_metering_note": null,
      "solar_installations": 0,
      "solar_capacity_mw": 0,
      "urdb_rate_name": "ELECTRIC HEATING",
      "urdb_rate_per_kwh": 0.1267,
      "updated_at": "2026-02-09"
    },
    {
      "utility_id": "18231",
      "utility_name": "City of Stuart, Iowa (Utility Company)",
      "state": "IA",
      "ownership_type": "municipal",
      "customer_count": 0,
      "residential_rate_per_kwh": 0.117,
      "rate_data_source": "OpenEI_URDB",
      "rate_structure": "tiered",
      "tou_available": false,
      "demand_charges": false,
      "has_net_metering": true,
      "net_metering_type": "NEM",
      "net_metering_note": null,
      "solar_installations": 0,
      "solar_capacity_mw": 0,
      "urdb_rate_name": "Residential Three Phase CP",
      "urdb_rate_per_kwh": 0.117,
      "updated_at": "2026-02-09"
    },
    {
      "utility_id": "18301",
      "utility_name": "City of Sumner, Iowa (Utility Company)",
      "state": "IA",
      "ownership_type": "municipal",
      "customer_count": 0,
      "residential_rate_per_kwh": 0.092,
      "rate_data_source": "OpenEI_URDB",
      "rate_structure": "flat",
      "tou_available": false,
      "demand_charges": false,
      "has_net_metering": true,
      "net_metering_type": "NEM",
      "net_metering_note": null,
      "solar_installations": 0,
      "solar_capacity_mw": 0,
      "urdb_rate_name": "Residential/Home Occupation Service",
      "urdb_rate_per_kwh": 0.092,
      "updated_at": "2026-02-09"
    },
    {
      "utility_id": "18947",
      "utility_name": "City of Tipton, Iowa (Utility Company)",
      "state": "IA",
      "ownership_type": "municipal",
      "customer_count": 0,
      "residential_rate_per_kwh": 0.1187,
      "rate_data_source": "OpenEI_URDB",
      "rate_structure": "flat",
      "tou_available": false,
      "demand_charges": false,
      "has_net_metering": true,
      "net_metering_type": "NEM",
      "net_metering_note": null,
      "solar_installations": 0,
      "solar_capacity_mw": 0,
      "urdb_rate_name": "RE1-All Residential",
      "urdb_rate_per_kwh": 0.1187,
      "updated_at": "2026-02-09"
    },
    {
      "utility_id": "19062",
      "utility_name": "City of Traer, Iowa (Utility Company)",
      "state": "IA",
      "ownership_type": "municipal",
      "customer_count": 0,
      "residential_rate_per_kwh": 0.0745,
      "rate_data_source": "OpenEI_URDB",
      "rate_structure": "tiered",
      "tou_available": false,
      "demand_charges": false,
      "has_net_metering": true,
      "net_metering_type": "NEM",
      "net_metering_note": null,
      "solar_installations": 0,
      "solar_capacity_mw": 0,
      "urdb_rate_name": "Heat Pump",
      "urdb_rate_per_kwh": 0.0745,
      "updated_at": "2026-02-09"
    },
    {
      "utility_id": "19843",
      "utility_name": "City of Villisca, Iowa (Utility Company)",
      "state": "IA",
      "ownership_type": "municipal",
      "customer_count": 0,
      "residential_rate_per_kwh": 0.088,
      "rate_data_source": "OpenEI_URDB",
      "rate_structure": "flat",
      "tou_available": false,
      "demand_charges": false,
      "has_net_metering": true,
      "net_metering_type": "NEM",
      "net_metering_note": null,
      "solar_installations": 0,
      "solar_capacity_mw": 0,
      "urdb_rate_name": "Rural Residential",
      "urdb_rate_per_kwh": 0.088,
      "updated_at": "2026-02-09"
    },
    {
      "utility_id": "19865",
      "utility_name": "City of Vinton, Iowa (Utility Company)",
      "state": "IA",
      "ownership_type": "municipal",
      "customer_count": 0,
      "residential_rate_per_kwh": 0.0778,
      "rate_data_source": "OpenEI_URDB",
      "rate_structure": "tiered",
      "tou_available": false,
      "demand_charges": false,
      "has_net_metering": true,
      "net_metering_type": "NEM",
      "net_metering_note": null,
      "solar_installations": 0,
      "solar_capacity_mw": 0,
      "urdb_rate_name": "Residential Rate",
      "urdb_rate_per_kwh": 0.0778,
      "updated_at": "2026-02-09"
    },
    {
      "utility_id": "20214",
      "utility_name": "Waverly Municipal Elec Utility",
      "state": "IA",
      "ownership_type": "municipal",
      "customer_count": 0,
      "residential_rate_per_kwh": 0.1138,
      "rate_data_source": "OpenEI_URDB",
      "rate_structure": "tou",
      "tou_available": true,
      "demand_charges": false,
      "has_net_metering": true,
      "net_metering_type": "NEM",
      "net_metering_note": null,
      "solar_installations": 0,
      "solar_capacity_mw": 0,
      "urdb_rate_name": "Electric Heat Rate for Residential Service",
      "urdb_rate_per_kwh": 0.1138,
      "updated_at": "2026-02-09"
    },
    {
      "utility_id": "20259",
      "utility_name": "City of Webster City, Iowa (Utility Company)",
      "state": "IA",
      "ownership_type": "municipal",
      "customer_count": 0,
      "residential_rate_per_kwh": 0.089,
      "rate_data_source": "OpenEI_URDB",
      "rate_structure": "flat",
      "tou_available": false,
      "demand_charges": false,
      "has_net_metering": true,
      "net_metering_type": "NEM",
      "net_metering_note": null,
      "solar_installations": 0,
      "solar_capacity_mw": 0,
      "urdb_rate_name": "Residential and Farm Rural Grain Bin",
      "urdb_rate_per_kwh": 0.089,
      "updated_at": "2026-02-09"
    },
    {
      "utility_id": "20364",
      "utility_name": "City of West Bend, Iowa (Utility Company)",
      "state": "IA",
      "ownership_type": "municipal",
      "customer_count": 0,
      "residential_rate_per_kwh": 0.082,
      "rate_data_source": "OpenEI_URDB",
      "rate_structure": "flat",
      "tou_available": false,
      "demand_charges": false,
      "has_net_metering": true,
      "net_metering_type": "NEM",
      "net_metering_note": null,
      "solar_installations": 0,
      "solar_capacity_mw": 0,
      "urdb_rate_name": "Residential Electric Rates",
      "urdb_rate_per_kwh": 0.082,
      "updated_at": "2026-02-09"
    },
    {
      "utility_id": "20380",
      "utility_name": "City of West Liberty, Iowa (Utility Company)",
      "state": "IA",
      "ownership_type": "municipal",
      "customer_count": 0,
      "residential_rate_per_kwh": 0.055,
      "rate_data_source": "OpenEI_URDB",
      "rate_structure": "tou",
      "tou_available": true,
      "demand_charges": false,
      "has_net_metering": true,
      "net_metering_type": "NEM",
      "net_metering_note": null,
      "solar_installations": 0,
      "solar_capacity_mw": 0,
      "urdb_rate_name": "Residential Customers",
      "urdb_rate_per_kwh": 0.055,
      "updated_at": "2026-02-09"
    },
    {
      "utility_id": "20396",
      "utility_name": "West Point Utility System",
      "state": "IA",
      "ownership_type": "IOU",
      "customer_count": 0,
      "residential_rate_per_kwh": 0.111,
      "rate_data_source": "OpenEI_URDB",
      "rate_structure": "flat",
      "tou_available": false,
      "demand_charges": false,
      "has_net_metering": true,
      "net_metering_type": "NEM",
      "net_metering_note": null,
      "solar_installations": 0,
      "solar_capacity_mw": 0,
      "urdb_rate_name": "Rural Resident and Farm All-Electric",
      "urdb_rate_per_kwh": 0.111,
      "updated_at": "2026-02-09"
    },
    {
      "utility_id": "20604",
      "utility_name": "City of Whittemore, Iowa (Utility Company)",
      "state": "IA",
      "ownership_type": "municipal",
      "customer_count": 0,
      "residential_rate_per_kwh": 0.101,
      "rate_data_source": "OpenEI_URDB",
      "rate_structure": "flat",
      "tou_available": false,
      "demand_charges": false,
      "has_net_metering": true,
      "net_metering_type": "NEM",
      "net_metering_note": null,
      "solar_installations": 0,
      "solar_capacity_mw": 0,
      "urdb_rate_name": "Residential",
      "urdb_rate_per_kwh": 0.101,
      "updated_at": "2026-02-09"
    },
    {
      "utility_id": "20789",
      "utility_name": "City of Wilton, Iowa (Utility Company)",
      "state": "IA",
      "ownership_type": "municipal",
      "customer_count": 0,
      "residential_rate_per_kwh": 0.1271,
      "rate_data_source": "OpenEI_URDB",
      "rate_structure": "tiered",
      "tou_available": false,
      "demand_charges": false,
      "has_net_metering": true,
      "net_metering_type": "NEM",
      "net_metering_note": null,
      "solar_installations": 0,
      "solar_capacity_mw": 0,
      "urdb_rate_name": "Residential",
      "urdb_rate_per_kwh": 0.1271,
      "updated_at": "2026-02-09"
    },
    {
      "utility_id": "20835",
      "utility_name": "City of Winterset, Iowa (Utility Company)",
      "state": "IA",
      "ownership_type": "municipal",
      "customer_count": 0,
      "residential_rate_per_kwh": 0.109,
      "rate_data_source": "OpenEI_URDB",
      "rate_structure": "flat",
      "tou_available": false,
      "demand_charges": false,
      "has_net_metering": true,
      "net_metering_type": "NEM",
      "net_metering_note": null,
      "solar_installations": 0,
      "solar_capacity_mw": 0,
      "urdb_rate_name": "RESIDENTIAL ELECTRIC RATES",
      "urdb_rate_per_kwh": 0.109,
      "updated_at": "2026-02-09"
    },
    {
      "utility_id": "20846",
      "utility_name": "City of Woolstock, Iowa (Utility Company)",
      "state": "IA",
      "ownership_type": "municipal",
      "customer_count": 0,
      "residential_rate_per_kwh": 0.0555,
      "rate_data_source": "OpenEI_URDB",
      "rate_structure": "tiered",
      "tou_available": false,
      "demand_charges": false,
      "has_net_metering": true,
      "net_metering_type": "NEM",
      "net_metering_note": null,
      "solar_installations": 0,
      "solar_capacity_mw": 0,
      "urdb_rate_name": "Residential",
      "urdb_rate_per_kwh": 0.0555,
      "updated_at": "2026-02-09"
    },
    {
      "utility_id": "20949",
      "utility_name": "City of Woodbine, Iowa (Utility Company)",
      "state": "IA",
      "ownership_type": "municipal",
      "customer_count": 0,
      "residential_rate_per_kwh": 0.086,
      "rate_data_source": "OpenEI_URDB",
      "rate_structure": "tou",
      "tou_available": true,
      "demand_charges": false,
      "has_net_metering": true,
      "net_metering_type": "NEM",
      "net_metering_note": null,
      "solar_installations": 0,
      "solar_capacity_mw": 0,
      "urdb_rate_name": "Water/House Heat (Non electric)",
      "urdb_rate_per_kwh": 0.086,
      "updated_at": "2026-02-09"
    },
    {
      "utility_id": "22646",
      "utility_name": "United Electric Coop, Inc (Iowa)",
      "state": "IA",
      "ownership_type": "cooperative",
      "customer_count": 0,
      "residential_rate_per_kwh": 0.117,
      "rate_data_source": "OpenEI_URDB",
      "rate_structure": "flat",
      "tou_available": false,
      "demand_charges": false,
      "has_net_metering": true,
      "net_metering_type": "NEM",
      "net_metering_note": null,
      "solar_installations": 0,
      "solar_capacity_mw": 0,
      "urdb_rate_name": "Residential (Single Phase Service)",
      "urdb_rate_per_kwh": 0.117,
      "updated_at": "2026-02-09"
    },
    {
      "utility_id": "26765",
      "utility_name": "Pella Cooperative Elec Assn",
      "state": "IA",
      "ownership_type": "cooperative",
      "customer_count": 0,
      "residential_rate_per_kwh": 0.0871,
      "rate_data_source": "OpenEI_URDB",
      "rate_structure": "tou",
      "tou_available": true,
      "demand_charges": false,
      "has_net_metering": true,
      "net_metering_type": "NEM",
      "net_metering_note": null,
      "solar_installations": 0,
      "solar_capacity_mw": 0,
      "urdb_rate_name": "Residential - Heat Plus Rate",
      "urdb_rate_per_kwh": 0.0871,
      "updated_at": "2026-02-09"
    },
    {
      "utility_id": "27269",
      "utility_name": "City of Stanhope, Iowa (Utility Company)",
      "state": "IA",
      "ownership_type": "municipal",
      "customer_count": 0,
      "residential_rate_per_kwh": 0.1242,
      "rate_data_source": "OpenEI_URDB",
      "rate_structure": "flat",
      "tou_available": false,
      "demand_charges": false,
      "has_net_metering": true,
      "net_metering_type": "NEM",
      "net_metering_note": null,
      "solar_installations": 0,
      "solar_capacity_mw": 0,
      "urdb_rate_name": "Residential rate-all electric-rate #10 (Single Phase) Composite",
      "urdb_rate_per_kwh": 0.1242,
      "updated_at": "2026-02-09"
    },
    {
      "utility_id": "40390",
      "utility_name": "City of Buffalo, Iowa (Utility Company)",
      "state": "IA",
      "ownership_type": "municipal",
      "customer_count": 0,
      "residential_rate_per_kwh": 0.1,
      "rate_data_source": "OpenEI_URDB",
      "rate_structure": "flat",
      "tou_available": false,
      "demand_charges": false,
      "has_net_metering": true,
      "net_metering_type": "NEM",
      "net_metering_note": null,
      "solar_installations": 0,
      "solar_capacity_mw": 0,
      "urdb_rate_name": "Electric Service Rates",
      "urdb_rate_per_kwh": 0.1,
      "updated_at": "2026-02-09"
    },
    {
      "utility_id": "49986",
      "utility_name": "Southwest Iowa Rural Elec Coop",
      "state": "IA",
      "ownership_type": "cooperative",
      "customer_count": 0,
      "residential_rate_per_kwh": 0.0962,
      "rate_data_source": "OpenEI_URDB",
      "rate_structure": "flat",
      "tou_available": false,
      "demand_charges": false,
      "has_net_metering": true,
      "net_metering_type": "NEM",
      "net_metering_note": null,
      "solar_installations": 0,
      "solar_capacity_mw": 0,
      "urdb_rate_name": "Residential Heat Plus",
      "urdb_rate_per_kwh": 0.0962,
      "updated_at": "2026-02-09"
    }
  ],
  "data_sources": [
    "EIA-861 (2024)",
    "OpenEI URDB",
    "DSIRE"
  ],
  "generated_at": "2026-02-09T06:23:38.876Z"
}